src/design/binary_BCD.sv
// ------------Tecnológico de Costa Rica-----------
// Escuela de Ingeniería Electrónica: Diseño Lógico

// Subsistema de despliegue en displays de 7 segmentos (BCD)
// Pablo Elizondo Espinoza
// Eduardo Tencio Solano
// Karina Quiros Avila

module binary_BCD(
    input logic reset,
    input logic [15 : 0] mult_result,
    input logic valid,
    output logic BCD_ready,
    output logic [15 : 0] BCD_code 
);
    logic [31 : 0] shift_reg;
    logic ready;
    integer i;

    always_ff @(posedge reset or posedge valid) begin
        if (reset) begin
            shift_reg <= 32'b0;
            ready <= 1'b0;
        end else if (valid) begin
            shift_reg = {16'b0, mult_result};

            for(i = 0; i < 16; i++) begin
                if(shift_reg[19 : 16] > 4)
                    shift_reg[19 : 16] = shift_reg[19 : 16] + 3;
                if(shift_reg[23 : 20] > 4)
                    shift_reg[23 : 20] = shift_reg[23 : 20] + 3;
                if(shift_reg[27 : 24] > 4)
                    shift_reg[27 : 24] = shift_reg[27 : 24] + 3;
                if(shift_reg[31 : 28] > 4)
                    shift_reg[31 : 28] = shift_reg[31 : 28] + 3;

                shift_reg = shift_reg << 1;
            end

            ready = 1'b1;
        end
    end

    assign BCD_code = shift_reg[31 : 16];
    assign BCD_ready = ready;
endmodule

src/sim/binary_BCD_tb.sv
module binary_BCD_tb();
    // Entradas
    logic reset;
    logic [15:0] mult_result;  // Cambiado a 16 bits
    logic valid;

    // Salidas
    logic [15:0] BCD_code;  // Cambiado a 16 bits

    // Instancia del módulo a probar
    binary_BCD uut (
        .reset(reset),
        .mult_result(mult_result),
        .valid(valid),
        .BCD_code(BCD_code)
    );

    // Tarea para mostrar el código BCD
    task display_BCD;
        input [15:0] BCD;  // Cambiado a 16 bits
        $display("BCD: %d%d%d%d", BCD[15:12], BCD[11:8], BCD[7:4], BCD[3:0]);
    endtask

    // Proceso de simulación
    initial begin
        // Crear archivo .vcd y empezar a volcar datos de señales
        $dumpfile("binary_BCD_tb.vcd");  // Nombre del archivo .vcd
        $dumpvars(0, binary_BCD_tb);  // Volcar todas las variables de este módulo

        // Inicializa las señales
        reset = 1;
        valid = 0;
        #10 reset = 0; // Quitar reset después de un tiempo
        
        // Prueba con diferentes números binarios
        // 1. Número: 45 (decimal)
        mult_result = 16'd45;  // Cambiado a 16 bits
        valid = 1;
        #10;
        valid = 0;
        #50; // Espera para permitir la conversión
        $display("Numero en decimal: 45");
        display_BCD(BCD_code);
        
        // 2. Número: 123 (decimal)
        mult_result = 16'd123;  // Cambiado a 16 bits
        valid = 1;
        #10;
        valid = 0;
        #50;
        $display("Numero en decimal: 123");
        display_BCD(BCD_code);

        // 3. Número: 999 (decimal)
        mult_result = 16'd999;  // Cambiado a 16 bits
        valid = 1;
        #10;
        valid = 0;
        #50;
        $display("Numero en decimal: 999");
        display_BCD(BCD_code);

        // 4. Número: 2047 (decimal)
        mult_result = 16'd2047;  // Cambiado a 16 bits
        valid = 1;
        #10;
        valid = 0;
        #50;
        $display("Numero en decimal: 2047");
        display_BCD(BCD_code);

        // 5. Número: 256 (decimal)
        mult_result = 16'd256;  // Cambiado a 16 bits
        valid = 1;
        #10;
        valid = 0;
        #50;
        $display("Numero en decimal: 256");
        display_BCD(BCD_code);

        $finish;
    end
endmodule

src/build/binary_BCD_tb.vcd
$date
	Thu Nov 07 09:13:02 2024
$end
$version
	Icarus Verilog
$end
$timescale
	1s
$end
$scope module binary_BCD_tb $end
$var wire 16 ! BCD_code [15:0] $end
$var reg 16 " mult_result [15:0] $end
$var reg 1 # reset $end
$var reg 1 $ valid $end
$scope module uut $end
$var wire 1 % BCD_ready $end
$var wire 16 & mult_result [15:0] $end
$var wire 1 # reset $end
$var wire 1 $ valid $end
$var wire 16 ' BCD_code [15:0] $end
$var reg 1 ( ready $end
$var reg 32 ) shift_reg [31:0] $end
$var integer 32 * i [31:0] $end
$upscope $end
$scope task display_BCD $end
$var reg 16 + BCD [15:0] $end
$upscope $end
$upscope $end
$enddefinitions $end
$comment Show the parameter values. $end
$dumpall
$end
#0
$dumpvars
bx +
bx *
b0 )
0(
b0 '
bx &
0%
0$
1#
bx "
b0 !
$end
#10
b1000101 !
b1000101 '
1%
1(
b10000 *
b10001010000000000000000 )
1$
b101101 "
b101101 &
0#
#20
0$
#70
b100100011 !
b100100011 '
b10000 *
b1001000110000000000000000 )
1$
b1111011 "
b1111011 &
b1000101 +
#80
0$
#130
b100110011001 !
b100110011001 '
b10000 *
b1001100110010000000000000000 )
1$
b1111100111 "
b1111100111 &
b100100011 +
#140
0$
#190
b10000001000111 !
b10000001000111 '
b10000 *
b100000010001110000000000000000 )
1$
b11111111111 "
b11111111111 &
b100110011001 +
#200
0$
#250
b1001010110 !
b1001010110 '
b10000 *
b10010101100000000000000000 )
1$
b100000000 "
b100000000 &
b10000001000111 +
#260
0$
#310
b1001010110 +
