src/design/module_cont_2b.sv
module module_cont_2b (

    input logic clk,
    input logic rst,
    input logic stop,

    output logic [1 : 0] cont_out //contador de 2 bits
);

    logic [1 : 0] cont = 0;
    
    always_ff @( posedge clk ) begin 

        if (!rst) begin
            cont <= 0;
        end

        else if (cont == 3) begin
            cont <= 0;
        end
        
        else if (!stop) begin
            cont <= cont + 1;
        end

    end

    assign cont_out = cont;

endmodule

src/sim/module_cont_2b_tb.sv
`timescale 1ns/1ps

module module_cont_2b_tb;


    logic clk;
    logic rst;
    logic stop;
    logic [1:0] cont_out;

    
    module_cont_2b uut (
        .clk (clk),
        .rst (rst),
        .stop (stop),
        .cont_out (cont_out)
    );


    initial begin
        
        clk = 0;
        rst = 1;
        stop = 0;

        //#30 rst = 0;

        //#30 rst = 1;

        #30 stop = 1;

        #120 stop = 0;

        #160 rst = 0;

        #170 stop = 1;

        #180 rst = 1;

        #200 stop = 0;

        #1000;
        $finish;
    end

    always begin
        clk = ~ clk;
        #10;
    end

    // Dumps de la simulación para visualización en GTKWAVE
    initial begin
        $dumpfile("module_cont_2b_tb.vcd");
        $dumpvars(0, module_cont_2b_tb);
    end

endmodule

src/build/module_cont_2b_tb.vcd
$date
	Fri Oct 25 12:55:55 2024
$end
$version
	Icarus Verilog
$end
$timescale
	1ps
$end
$scope module module_cont_2b_tb $end
$var wire 2 ! cont_out [1:0] $end
$var reg 1 " clk $end
$var reg 1 # rst $end
$var reg 1 $ stop $end
$scope module uut $end
$var wire 1 " clk $end
$var wire 2 % cont_out [1:0] $end
$var wire 1 # rst $end
$var wire 1 $ stop $end
$var reg 2 & cont [1:0] $end
$upscope $end
$upscope $end
$enddefinitions $end
$comment Show the parameter values. $end
$dumpall
$end
#0
$dumpvars
b1 &
b1 %
0$
1#
1"
b1 !
$end
#10000
0"
#20000
b10 !
b10 %
b10 &
1"
#30000
0"
1$
#40000
1"
#50000
0"
#60000
1"
#70000
0"
#80000
1"
#90000
0"
#100000
1"
#110000
0"
#120000
1"
#130000
0"
#140000
1"
#150000
0"
0$
#160000
b11 !
b11 %
b11 &
1"
#170000
0"
#180000
b0 !
b0 %
b0 &
1"
#190000
0"
#200000
b1 !
b1 %
b1 &
1"
#210000
0"
#220000
b10 !
b10 %
b10 &
1"
#230000
0"
#240000
b11 !
b11 %
b11 &
1"
#250000
0"
#260000
b0 !
b0 %
b0 &
1"
#270000
0"
#280000
b1 !
b1 %
b1 &
1"
#290000
0"
#300000
b10 !
b10 %
b10 &
1"
#310000
0"
0#
#320000
b0 !
b0 %
b0 &
1"
#330000
0"
#340000
1"
#350000
0"
#360000
1"
#370000
0"
#380000
1"
#390000
0"
#400000
1"
#410000
0"
#420000
1"
#430000
0"
#440000
1"
#450000
0"
#460000
1"
#470000
0"
#480000
1"
1$
#490000
0"
#500000
1"
#510000
0"
#520000
1"
#530000
0"
#540000
1"
#550000
0"
#560000
1"
#570000
0"
#580000
1"
#590000
0"
#600000
1"
#610000
0"
#620000
1"
#630000
0"
#640000
1"
#650000
0"
#660000
1"
1#
#670000
0"
#680000
1"
#690000
0"
#700000
1"
#710000
0"
#720000
1"
#730000
0"
#740000
1"
#750000
0"
#760000
1"
#770000
0"
#780000
1"
#790000
0"
#800000
1"
#810000
0"
#820000
1"
#830000
0"
#840000
1"
#850000
0"
#860000
b1 !
b1 %
b1 &
1"
0$
#870000
0"
#880000
b10 !
b10 %
b10 &
1"
#890000
0"
#900000
b11 !
b11 %
b11 &
1"
#910000
0"
#920000
b0 !
b0 %
b0 &
1"
#930000
0"
#940000
b1 !
b1 %
b1 &
1"
#950000
0"
#960000
b10 !
b10 %
b10 &
1"
#970000
0"
#980000
b11 !
b11 %
b11 &
1"
#990000
0"
#1000000
b0 !
b0 %
b0 &
1"
#1010000
0"
#1020000
b1 !
b1 %
b1 &
1"
#1030000
0"
#1040000
b10 !
b10 %
b10 &
1"
#1050000
0"
#1060000
b11 !
b11 %
b11 &
1"
#1070000
0"
#1080000
b0 !
b0 %
b0 &
1"
#1090000
0"
#1100000
b1 !
b1 %
b1 &
1"
#1110000
0"
#1120000
b10 !
b10 %
b10 &
1"
#1130000
0"
#1140000
b11 !
b11 %
b11 &
1"
#1150000
0"
#1160000
b0 !
b0 %
b0 &
1"
#1170000
0"
#1180000
b1 !
b1 %
b1 &
1"
#1190000
0"
#1200000
b10 !
b10 %
b10 &
1"
#1210000
0"
#1220000
b11 !
b11 %
b11 &
1"
#1230000
0"
#1240000
b0 !
b0 %
b0 &
1"
#1250000
0"
#1260000
b1 !
b1 %
b1 &
1"
#1270000
0"
#1280000
b10 !
b10 %
b10 &
1"
#1290000
0"
#1300000
b11 !
b11 %
b11 &
1"
#1310000
0"
#1320000
b0 !
b0 %
b0 &
1"
#1330000
0"
#1340000
b1 !
b1 %
b1 &
1"
#1350000
0"
#1360000
b10 !
b10 %
b10 &
1"
#1370000
0"
#1380000
b11 !
b11 %
b11 &
1"
#1390000
0"
#1400000
b0 !
b0 %
b0 &
1"
#1410000
0"
#1420000
b1 !
b1 %
b1 &
1"
#1430000
0"
#1440000
b10 !
b10 %
b10 &
1"
#1450000
0"
#1460000
b11 !
b11 %
b11 &
1"
#1470000
0"
#1480000
b0 !
b0 %
b0 &
1"
#1490000
0"
#1500000
b1 !
b1 %
b1 &
1"
#1510000
0"
#1520000
b10 !
b10 %
b10 &
1"
#1530000
0"
#1540000
b11 !
b11 %
b11 &
1"
#1550000
0"
#1560000
b0 !
b0 %
b0 &
1"
#1570000
0"
#1580000
b1 !
b1 %
b1 &
1"
#1590000
0"
#1600000
b10 !
b10 %
b10 &
1"
#1610000
0"
#1620000
b11 !
b11 %
b11 &
1"
#1630000
0"
#1640000
b0 !
b0 %
b0 &
1"
#1650000
0"
#1660000
b1 !
b1 %
b1 &
1"
#1670000
0"
#1680000
b10 !
b10 %
b10 &
1"
#1690000
0"
#1700000
b11 !
b11 %
b11 &
1"
#1710000
0"
#1720000
b0 !
b0 %
b0 &
1"
#1730000
0"
#1740000
b1 !
b1 %
b1 &
1"
#1750000
0"
#1760000
b10 !
b10 %
b10 &
1"
#1770000
0"
#1780000
b11 !
b11 %
b11 &
1"
#1790000
0"
#1800000
b0 !
b0 %
b0 &
1"
#1810000
0"
#1820000
b1 !
b1 %
b1 &
1"
#1830000
0"
#1840000
b10 !
b10 %
b10 &
1"
#1850000
0"
#1860000
b11 !
b11 %
b11 &
1"
