src/design/module_Debounce.sv
module module_Debounce (
    input logic clk,               
    input logic [3:0] filas_in,    // Entrada de 4 bits (información sobre la fila)
    output logic enable            // Señal de habilitación, activada cuando el dato está estabilizado
);

    // Registro de desplazamiento de 16 bits para almacenar los valores de fila
    logic [15:0] filas_reg;

    // Proceso secuencial para desplazar los bits de la fila en cada flanco positivo del reloj
    always @(posedge clk) begin
        filas_reg <= {filas_in, filas_reg[15:4]}; // Desplaza los bits y añade filas_in en los 4 MSB
    end

    // Lógica combinacional para determinar si la fila está estabilizada
    always_comb begin
        enable = (filas_reg[15:12] == filas_reg[11:8]) &&
                 (filas_reg[11:8] == filas_reg[7:4]) &&
                 (filas_reg[7:4] == filas_reg[3:0]);
    end

endmodule

src/sim/module_DeBounce_tb.sv
`timescale 1 ns / 100 ps

module module_Debounce_tb;

    // Señales de entrada y salida
    logic clk;
    logic [3:0] filas_in;
    logic enable;

    // Instanciación del módulo de debounce
    module_Debounce uut (
        .clk(clk),
        .filas_in(filas_in),
        .enable(enable)
    );

    // Generador de reloj (1 kHz -> 1000 ns por ciclo)
    always #500 clk = ~clk;

    initial begin
        // Inicialización de señales
        clk = 0;
        filas_in = 4'b1111;
        
        // Generación de un rebote en la señal `filas_in`
        // Cambios rápidos de estado para simular ruido de rebote
        #1000 filas_in = 4'b1110;    // Primer cambio
        #1000 filas_in = 4'b1111;    // Vuelve al estado inicial
        #1000 filas_in = 4'b1110;    // Rebote
        #1000 filas_in = 4'b1111;    // Vuelve al estado inicial
        #1000 filas_in = 4'b1110;    // Cambio de nuevo
        #10000 filas_in = 4'b1110;   // Mantiene el estado para estabilizar

        // Después de mantener `filas_in` estable, `enable` debería activarse
        #20000 $finish;                // Fin de la simulación
    end

    // Monitor para observar los cambios en el tiempo
    initial begin
        $monitor("Time=%0t | clk=%b | filas_in=%b | enable=%b",
                 $time, clk, filas_in, enable);
    end

    initial begin
        $dumpfile("module_Debounce_tb.vcd");
        $dumpvars(0, module_Debounce_tb);
    end
endmodule

src/build/module_Debounce_tb.vcd
$date
	Fri Nov 08 17:39:08 2024
$end
$version
	Icarus Verilog
$end
$timescale
	100ps
$end
$scope module module_Debounce_tb $end
$var wire 1 ! enable $end
$var reg 1 " clk $end
$var reg 4 # filas_in [3:0] $end
$scope module uut $end
$var wire 1 " clk $end
$var wire 4 $ filas_in [3:0] $end
$var reg 1 ! enable $end
$var reg 16 % filas_reg [15:0] $end
$upscope $end
$upscope $end
$enddefinitions $end
$comment Show the parameter values. $end
$dumpall
$end
#0
$dumpvars
bx %
b1111 $
b1111 #
0"
x!
$end
#5000
b1111xxxxxxxxxxxx %
1"
#10000
0"
b1110 #
b1110 $
#15000
0!
b11101111xxxxxxxx %
1"
#20000
0"
b1111 #
b1111 $
#25000
b111111101111xxxx %
1"
#30000
0"
b1110 #
b1110 $
#35000
b1110111111101111 %
1"
#40000
0"
b1111 #
b1111 $
#45000
b1111111011111110 %
1"
#50000
0"
b1110 #
b1110 $
#55000
b1110111111101111 %
1"
#60000
0"
#65000
b1110111011111110 %
1"
#70000
0"
#75000
b1110111011101111 %
1"
#80000
0"
#85000
1!
b1110111011101110 %
1"
