src/design/module_divisor.sv
module module_divisor # (

    parameter COUNT = 13500 

) (

    input logic clk,
    input logic rst,

    output logic prd_out //periodo salida
);

    localparam WIDTH_COUNT = $clog2(COUNT); //Cantidad de bits para representar el numero
    
    logic [WIDTH_COUNT - 1 : 0] clk_counter = 0;//Contador
    logic prd_new = 0;

    always_ff @( posedge clk ) begin 
        
        if (!rst) begin
            prd_new <= 0;
            clk_counter <= 0;
        end

        else if (clk_counter == COUNT -1) begin
            prd_new <= ~prd_new;
            clk_counter <= 0;
        end

        else begin
            clk_counter <= clk_counter + 1;
        end
    end

    assign prd_out = prd_new;

endmodule

src/sim/module_divisor_tb.sv
`timescale 1ns/1ps

module module_divisor_tb;

    parameter COUNT = 13500;

    logic clk;
    logic rst;
    logic prd_out;

    // Instancia del módulo bajo prueba (module_divisor)
    module_divisor # (.COUNT(COUNT)) uut (
        .clk (clk),
        .rst (rst),
        .prd_out (prd_out)
    );


    initial begin
        
        clk = 0;
        rst = 1;

        #20;

        rst = 0;

        #20

        rst = 1;

        # 2000000;
        $finish;
    end

    always begin
        clk = ~ clk;
        #18;
    end

    // Dumps de la simulación para visualización en GTKWAVE
    initial begin
        $dumpfile("module_divisor_tb.vcd");
        $dumpvars(0, module_divisor_tb);
    end

endmodule

src/build/module_divisor_tb.vcd
$date
	Wed Oct 23 22:48:52 2024
$end
$version
	Icarus Verilog
$end
$timescale
	1ps
$end
$scope module module_divisor_tb $end
$var wire 1 ! prd_out $end
$var parameter 32 " COUNT $end
$var reg 1 # clk $end
$var reg 1 $ rst $end
$scope module uut $end
$var wire 1 # clk $end
$var wire 1 ! prd_out $end
$var wire 1 $ rst $end
$var parameter 32 % COUNT $end
$var parameter 32 & WIDTH_COUNT $end
$var reg 14 ' clk_counter [13:0] $end
$var reg 1 ( prd_new $end
$upscope $end
$upscope $end
$enddefinitions $end
$comment Show the parameter values. $end
$dumpall
b1110 &
b11010010111100 %
b11010010111100 "
$end
#0
$dumpvars
0(
b1 '
1$
1#
0!
$end
#18000
0#
#20000
0$
#36000
b0 '
1#
#40000
1$
#54000
0#
#72000
b1 '
1#
#90000
0#
#108000
b10 '
1#
#126000
0#
#144000
b11 '
1#
#162000
0#
#180000
b100 '
1#
#198000
0#
#216000
b101 '
1#
#234000
0#
#252000
b110 '
1#
#270000
0#
#288000
b111 '
1#
#306000
0#
#324000
b1000 '
1#
#342000
0#
#360000
b1001 '
1#
#378000
0#
#396000
b1010 '
1#
#414000
0#
#432000
b1011 '
1#
#450000
0#
#468000
b1100 '
1#
#486000
0#
#504000
b1101 '
1#
#522000
0#
#540000
b1110 '
1#
#558000
0#
#576000
b1111 '
1#
#594000
0#
#612000
b10000 '
1#
#630000
0#
#648000
b10001 '
1#
#666000
0#
#684000
b10010 '
1#
#702000
0#
#720000
b10011 '
1#
#738000
0#
#756000
b10100 '
1#
#774000
0#
#792000
b10101 '
1#
#810000
0#
#828000
b10110 '
1#
#846000
0#
#864000
b10111 '
1#
#882000
0#
#900000
b11000 '
1#
#918000
0#
#936000
b11001 '
1#
#954000
0#
#972000
b11010 '
1#
#990000
0#
#1008000
b11011 '
1#
#1026000
0#
#1044000
b11100 '
1#
#1062000
0#
#1080000
b11101 '
1#
#1098000
0#
#1116000
b11110 '
1#
#1134000
0#
#1152000
b11111 '
1#
#1170000
0#
#1188000
b100000 '
1#
#1206000
0#
#1224000
b100001 '
1#
#1242000
0#
#1260000
b100010 '
1#
#1278000
0#
#1296000
b100011 '
1#
#1314000
0#
#1332000
b100100 '
1#
#1350000
0#
#1368000
b100101 '
1#
#1386000
0#
#1404000
b100110 '
1#
#1422000
0#
#1440000
b100111 '
1#
#1458000
0#
#1476000
b101000 '
1#
#1494000
0#
#1512000
b101001 '
1#
#1530000
0#
#1548000
b101010 '
1#
#1566000
0#
#1584000
b101011 '
1#
#1602000
0#
#1620000
b101100 '
1#
#1638000
0#
#1656000
b101101 '
1#
#1674000
0#
#1692000
b101110 '
1#
#1710000
0#
#1728000
b101111 '
1#
#1746000
0#
#1764000
b110000 '
1#
#1782000
0#
#1800000
b110001 '
1#
#1818000
0#
#1836000
b110010 '
1#
#1854000
0#
#1872000
b110011 '
1#
#1890000
0#
#1908000
b110100 '
1#
#1926000
0#
#1944000
b110101 '
1#
#1962000
0#
#1980000
b110110 '
1#
#1998000
0#
#2016000
b110111 '
1#
#2034000
0#
#2052000
b111000 '
1#
#2070000
0#
#2088000
b111001 '
1#
#2106000
0#
#2124000
b111010 '
1#
#2142000
0#
#2160000
b111011 '
1#
#2178000
0#
#2196000
b111100 '
1#
#2214000
0#
#2232000
b111101 '
1#
#2250000
0#
#2268000
b111110 '
1#
#2286000
0#
#2304000
b111111 '
1#
#2322000
0#
#2340000
b1000000 '
1#
#2358000
0#
#2376000
b1000001 '
1#
#2394000
0#
#2412000
b1000010 '
1#
#2430000
0#
#2448000
b1000011 '
1#
#2466000
0#
#2484000
b1000100 '
1#
#2502000
0#
#2520000
b1000101 '
1#
#2538000
0#
#2556000
b1000110 '
1#
#2574000
0#
#2592000
b1000111 '
1#
#2610000
0#
#2628000
b1001000 '
1#
#2646000
0#
#2664000
b1001001 '
1#
#2682000
0#
#2700000
b1001010 '
1#
#2718000
0#
#2736000
b1001011 '
1#
#2754000
0#
#2772000
b1001100 '
1#
#2790000
0#
#2808000
b1001101 '
1#
#2826000
0#
#2844000
b1001110 '
1#
#2862000
0#
#2880000
b1001111 '
1#
#2898000
0#
#2916000
b1010000 '
1#
#2934000
0#
#2952000
b1010001 '
1#
#2970000
0#
#2988000
b1010010 '
1#
#3006000
0#
#3024000
b1010011 '
1#
#3042000
0#
#3060000
b1010100 '
1#
#3078000
0#
#3096000
b1010101 '
1#
#3114000
0#
#3132000
b1010110 '
1#
#3150000
0#
#3168000
b1010111 '
1#
#3186000
0#
#3204000
b1011000 '
1#
#3222000
0#
#3240000
b1011001 '
1#
#3258000
0#
#3276000
b1011010 '
1#
#3294000
0#
#3312000
b1011011 '
1#
#3330000
0#
#3348000
b1011100 '
1#
#3366000
0#
#3384000
b1011101 '
1#
#3402000
0#
#3420000
b1011110 '
1#
#3438000
0#
#3456000
b1011111 '
1#
#3474000
0#
#3492000
b1100000 '
1#
#3510000
0#
#3528000
b1100001 '
1#
#3546000
0#
#3564000
b1100010 '
1#
#3582000
0#
#3600000
b1100011 '
1#
#3618000
0#
#3636000
b1100100 '
1#
#3654000
0#
#3672000
b1100101 '
1#
#3690000
0#
#3708000
b1100110 '
1#
#3726000
0#
#3744000
b1100111 '
1#
#3762000
0#
#3780000
b1101000 '
1#
#3798000
0#
#3816000
b1101001 '
1#
#3834000
0#
#3852000
b1101010 '
1#
#3870000
0#
#3888000
b1101011 '
1#
#3906000
0#
#3924000
b1101100 '
1#
#3942000
0#
#3960000
b1101101 '
1#
#3978000
0#
#3996000
b1101110 '
1#
#4014000
0#
#4032000
b1101111 '
1#
#4050000
0#
#4068000
b1110000 '
1#
#4086000
0#
#4104000
b1110001 '
1#
#4122000
0#
#4140000
b1110010 '
1#
#4158000
0#
#4176000
b1110011 '
1#
#4194000
0#
#4212000
b1110100 '
1#
#4230000
0#
#4248000
b1110101 '
1#
#4266000
0#
#4284000
b1110110 '
1#
#4302000
0#
#4320000
b1110111 '
1#
#4338000
0#
#4356000
b1111000 '
1#
#4374000
0#
#4392000
b1111001 '
1#
#4410000
0#
#4428000
b1111010 '
1#
#4446000
0#
#4464000
b1111011 '
1#
#4482000
0#
#4500000
b1111100 '
1#
#4518000
0#
#4536000
b1111101 '
1#
#4554000
0#
#4572000
b1111110 '
1#
#4590000
0#
#4608000
b1111111 '
1#
#4626000
0#
#4644000
b10000000 '
1#
#4662000
0#
#4680000
b10000001 '
1#
#4698000
0#
#4716000
b10000010 '
1#
#4734000
0#
#4752000
b10000011 '
1#
#4770000
0#
#4788000
b10000100 '
1#
#4806000
0#
#4824000
b10000101 '
1#
#4842000
0#
#4860000
b10000110 '
1#
#4878000
0#
#4896000
b10000111 '
1#
#4914000
0#
#4932000
b10001000 '
1#
#4950000
0#
#4968000
b10001001 '
1#
#4986000
0#
#5004000
b10001010 '
1#
#5022000
0#
#5040000
b10001011 '
1#
#5058000
0#
#5076000
b10001100 '
1#
#5094000
0#
#5112000
b10001101 '
1#
#5130000
0#
#5148000
b10001110 '
1#
#5166000
0#
#5184000
b10001111 '
1#
#5202000
0#
#5220000
b10010000 '
1#
#5238000
0#
#5256000
b10010001 '
1#
#5274000
0#
#5292000
b10010010 '
1#
#5310000
0#
#5328000
b10010011 '
1#
#5346000
0#
#5364000
b10010100 '
1#
#5382000
0#
#5400000
b10010101 '
1#
#5418000
0#
#5436000
b10010110 '
1#
#5454000
0#
#5472000
b10010111 '
1#
#5490000
0#
#5508000
b10011000 '
1#
#5526000
0#
#5544000
b10011001 '
1#
#5562000
0#
#5580000
b10011010 '
1#
#5598000
0#
#5616000
b10011011 '
1#
#5634000
0#
#5652000
b10011100 '
1#
#5670000
0#
#5688000
b10011101 '
1#
#5706000
0#
#5724000
b10011110 '
1#
#5742000
0#
#5760000
b10011111 '
1#
#5778000
0#
#5796000
b10100000 '
1#
#5814000
0#
#5832000
b10100001 '
1#
#5850000
0#
#5868000
b10100010 '
1#
#5886000
0#
#5904000
b10100011 '
1#
#5922000
0#
#5940000
b10100100 '
1#
#5958000
0#
#5976000
b10100101 '
1#
#5994000
0#
#6012000
b10100110 '
1#
#6030000
0#
#6048000
b10100111 '
1#
#6066000
0#
#6084000
b10101000 '
1#
#6102000
0#
#6120000
b10101001 '
1#
#6138000
0#
#6156000
b10101010 '
1#
#6174000
0#
#6192000
b10101011 '
1#
#6210000
0#
#6228000
b10101100 '
1#
#6246000
0#
#6264000
b10101101 '
1#
#6282000
0#
#6300000
b10101110 '
1#
#6318000
0#
#6336000
b10101111 '
1#
#6354000
0#
#6372000
b10110000 '
1#
#6390000
0#
#6408000
b10110001 '
1#
#6426000
0#
#6444000
b10110010 '
1#
#6462000
0#
#6480000
b10110011 '
1#
#6498000
0#
#6516000
b10110100 '
1#
#6534000
0#
#6552000
b10110101 '
1#
#6570000
0#
#6588000
b10110110 '
1#
#6606000
0#
#6624000
b10110111 '
1#
#6642000
0#
#6660000
b10111000 '
1#
#6678000
0#
#6696000
b10111001 '
1#
#6714000
0#
#6732000
b10111010 '
1#
#6750000
0#
#6768000
b10111011 '
1#
#6786000
0#
#6804000
b10111100 '
1#
#6822000
0#
#6840000
b10111101 '
1#
#6858000
0#
#6876000
b10111110 '
1#
#6894000
0#
#6912000
b10111111 '
1#
#6930000
0#
#6948000
b11000000 '
1#
#6966000
0#
#6984000
b11000001 '
1#
#7002000
0#
#7020000
b11000010 '
1#
#7038000
0#
#7056000
b11000011 '
1#
#7074000
0#
#7092000
b11000100 '
1#
#7110000
0#
#7128000
b11000101 '
1#
#7146000
0#
#7164000
b11000110 '
1#
#7182000
0#
#7200000
b11000111 '
1#
#7218000
0#
#7236000
b11001000 '
1#
#7254000
0#
#7272000
b11001001 '
1#
#7290000
0#
#7308000
b11001010 '
1#
#7326000
0#
#7344000
b11001011 '
1#
#7362000
0#
#7380000
b11001100 '
1#
#7398000
0#
#7416000
b11001101 '
1#
#7434000
0#
#7452000
b11001110 '
1#
#7470000
0#
#7488000
b11001111 '
1#
#7506000
0#
#7524000
b11010000 '
1#
#7542000
0#
#7560000
b11010001 '
1#
#7578000
0#
#7596000
b11010010 '
1#
#7614000
0#
#7632000
b11010011 '
1#
#7650000
0#
#7668000
b11010100 '
1#
#7686000
0#
#7704000
b11010101 '
1#
#7722000
0#
#7740000
b11010110 '
1#
#7758000
0#
#7776000
b11010111 '
1#
#7794000
0#
#7812000
b11011000 '
1#
#7830000
0#
#7848000
b11011001 '
1#
#7866000
0#
#7884000
b11011010 '
1#
#7902000
0#
#7920000
b11011011 '
1#
#7938000
0#
#7956000
b11011100 '
1#
#7974000
0#
#7992000
b11011101 '
1#
#8010000
0#
#8028000
b11011110 '
1#
#8046000
0#
#8064000
b11011111 '
1#
#8082000
0#
#8100000
b11100000 '
1#
#8118000
0#
#8136000
b11100001 '
1#
#8154000
0#
#8172000
b11100010 '
1#
#8190000
0#
#8208000
b11100011 '
1#
#8226000
0#
#8244000
b11100100 '
1#
#8262000
0#
#8280000
b11100101 '
1#
#8298000
0#
#8316000
b11100110 '
1#
#8334000
0#
#8352000
b11100111 '
1#
#8370000
0#
#8388000
b11101000 '
1#
#8406000
0#
#8424000
b11101001 '
1#
#8442000
0#
#8460000
b11101010 '
1#
#8478000
0#
#8496000
b11101011 '
1#
#8514000
0#
#8532000
b11101100 '
1#
#8550000
0#
#8568000
b11101101 '
1#
#8586000
0#
#8604000
b11101110 '
1#
#8622000
0#
#8640000
b11101111 '
1#
#8658000
0#
#8676000
b11110000 '
1#
#8694000
0#
#8712000
b11110001 '
1#
#8730000
0#
#8748000
b11110010 '
1#
#8766000
0#
#8784000
b11110011 '
1#
#8802000
0#
#8820000
b11110100 '
1#
#8838000
0#
#8856000
b11110101 '
1#
#8874000
0#
#8892000
b11110110 '
1#
#8910000
0#
#8928000
b11110111 '
1#
#8946000
0#
#8964000
b11111000 '
1#
#8982000
0#
#9000000
b11111001 '
1#
#9018000
0#
#9036000
b11111010 '
1#
#9054000
0#
#9072000
b11111011 '
1#
#9090000
0#
#9108000
b11111100 '
1#
#9126000
0#
#9144000
b11111101 '
1#
#9162000
0#
#9180000
b11111110 '
1#
#9198000
0#
#9216000
b11111111 '
1#
#9234000
0#
#9252000
b100000000 '
1#
#9270000
0#
#9288000
b100000001 '
1#
#9306000
0#
#9324000
b100000010 '
1#
#9342000
0#
#9360000
b100000011 '
1#
#9378000
0#
#9396000
b100000100 '
1#
#9414000
0#
#9432000
b100000101 '
1#
#9450000
0#
#9468000
b100000110 '
1#
#9486000
0#
#9504000
b100000111 '
1#
#9522000
0#
#9540000
b100001000 '
1#
#9558000
0#
#9576000
b100001001 '
1#
#9594000
0#
#9612000
b100001010 '
1#
#9630000
0#
#9648000
b100001011 '
1#
#9666000
0#
#9684000
b100001100 '
1#
#9702000
0#
#9720000
b100001101 '
1#
#9738000
0#
#9756000
b100001110 '
1#
#9774000
0#
#9792000
b100001111 '
1#
#9810000
0#
#9828000
b100010000 '
1#
#9846000
0#
#9864000
b100010001 '
1#
#9882000
0#
#9900000
b100010010 '
1#
#9918000
0#
#9936000
b100010011 '
1#
#9954000
0#
#9972000
b100010100 '
1#
#9990000
0#
#10008000
b100010101 '
1#
#10026000
0#
#10044000
b100010110 '
1#
#10062000
0#
#10080000
b100010111 '
1#
#10098000
0#
#10116000
b100011000 '
1#
#10134000
0#
#10152000
b100011001 '
1#
#10170000
0#
#10188000
b100011010 '
1#
#10206000
0#
#10224000
b100011011 '
1#
#10242000
0#
#10260000
b100011100 '
1#
#10278000
0#
#10296000
b100011101 '
1#
#10314000
0#
#10332000
b100011110 '
1#
#10350000
0#
#10368000
b100011111 '
1#
#10386000
0#
#10404000
b100100000 '
1#
#10422000
0#
#10440000
b100100001 '
1#
#10458000
0#
#10476000
b100100010 '
1#
#10494000
0#
#10512000
b100100011 '
1#
#10530000
0#
#10548000
b100100100 '
1#
#10566000
0#
#10584000
b100100101 '
1#
#10602000
0#
#10620000
b100100110 '
1#
#10638000
0#
#10656000
b100100111 '
1#
#10674000
0#
#10692000
b100101000 '
1#
#10710000
0#
#10728000
b100101001 '
1#
#10746000
0#
#10764000
b100101010 '
1#
#10782000
0#
#10800000
b100101011 '
1#
#10818000
0#
#10836000
b100101100 '
1#
#10854000
0#
#10872000
b100101101 '
1#
#10890000
0#
#10908000
b100101110 '
1#
#10926000
0#
#10944000
b100101111 '
1#
#10962000
0#
#10980000
b100110000 '
1#
#10998000
0#
#11016000
b100110001 '
1#
#11034000
0#
#11052000
b100110010 '
1#
#11070000
0#
#11088000
b100110011 '
1#
#11106000
0#
#11124000
b100110100 '
1#
#11142000
0#
#11160000
b100110101 '
1#
#11178000
0#
#11196000
b100110110 '
1#
#11214000
0#
#11232000
b100110111 '
1#
#11250000
0#
#11268000
b100111000 '
1#
#11286000
0#
#11304000
b100111001 '
1#
#11322000
0#
#11340000
b100111010 '
1#
#11358000
0#
#11376000
b100111011 '
1#
#11394000
0#
#11412000
b100111100 '
1#
#11430000
0#
#11448000
b100111101 '
1#
#11466000
0#
#11484000
b100111110 '
1#
#11502000
0#
#11520000
b100111111 '
1#
#11538000
0#
#11556000
b101000000 '
1#
#11574000
0#
#11592000
b101000001 '
1#
#11610000
0#
#11628000
b101000010 '
1#
#11646000
0#
#11664000
b101000011 '
1#
#11682000
0#
#11700000
b101000100 '
1#
#11718000
0#
#11736000
b101000101 '
1#
#11754000
0#
#11772000
b101000110 '
1#
#11790000
0#
#11808000
b101000111 '
1#
#11826000
0#
#11844000
b101001000 '
1#
#11862000
0#
#11880000
b101001001 '
1#
#11898000
0#
#11916000
b101001010 '
1#
#11934000
0#
#11952000
b101001011 '
1#
#11970000
0#
#11988000
b101001100 '
1#
#12006000
0#
#12024000
b101001101 '
1#
#12042000
0#
#12060000
b101001110 '
1#
#12078000
0#
#12096000
b101001111 '
1#
#12114000
0#
#12132000
b101010000 '
1#
#12150000
0#
#12168000
b101010001 '
1#
#12186000
0#
#12204000
b101010010 '
1#
#12222000
0#
#12240000
b101010011 '
1#
#12258000
0#
#12276000
b101010100 '
1#
#12294000
0#
#12312000
b101010101 '
1#
#12330000
0#
#12348000
b101010110 '
1#
#12366000
0#
#12384000
b101010111 '
1#
#12402000
0#
#12420000
b101011000 '
1#
#12438000
0#
#12456000
b101011001 '
1#
#12474000
0#
#12492000
b101011010 '
1#
#12510000
0#
#12528000
b101011011 '
1#
#12546000
0#
#12564000
b101011100 '
1#
#12582000
0#
#12600000
b101011101 '
1#
#12618000
0#
#12636000
b101011110 '
1#
#12654000
0#
#12672000
b101011111 '
1#
#12690000
0#
#12708000
b101100000 '
1#
#12726000
0#
#12744000
b101100001 '
1#
#12762000
0#
#12780000
b101100010 '
1#
#12798000
0#
#12816000
b101100011 '
1#
#12834000
0#
#12852000
b101100100 '
1#
#12870000
0#
#12888000
b101100101 '
1#
#12906000
0#
#12924000
b101100110 '
1#
#12942000
0#
#12960000
b101100111 '
1#
#12978000
0#
#12996000
b101101000 '
1#
#13014000
0#
#13032000
b101101001 '
1#
#13050000
0#
#13068000
b101101010 '
1#
#13086000
0#
#13104000
b101101011 '
1#
#13122000
0#
#13140000
b101101100 '
1#
#13158000
0#
#13176000
b101101101 '
1#
#13194000
0#
#13212000
b101101110 '
1#
#13230000
0#
#13248000
b101101111 '
1#
#13266000
0#
#13284000
b101110000 '
1#
#13302000
0#
#13320000
b101110001 '
1#
#13338000
0#
#13356000
b101110010 '
1#
#13374000
0#
#13392000
b101110011 '
1#
#13410000
0#
#13428000
b101110100 '
1#
#13446000
0#
#13464000
b101110101 '
1#
#13482000
0#
#13500000
b101110110 '
1#
#13518000
0#
#13536000
b101110111 '
1#
#13554000
0#
#13572000
b101111000 '
1#
#13590000
0#
#13608000
b101111001 '
1#
#13626000
0#
#13644000
b101111010 '
1#
#13662000
0#
#13680000
b101111011 '
1#
#13698000
0#
#13716000
b101111100 '
1#
#13734000
0#
#13752000
b101111101 '
1#
#13770000
0#
#13788000
b101111110 '
1#
#13806000
0#
#13824000
b101111111 '
1#
#13842000
0#
#13860000
b110000000 '
1#
#13878000
0#
#13896000
b110000001 '
1#
#13914000
0#
#13932000
b110000010 '
1#
#13950000
0#
#13968000
b110000011 '
1#
#13986000
0#
#14004000
b110000100 '
1#
#14022000
0#
#14040000
b110000101 '
1#
#14058000
0#
#14076000
b110000110 '
1#
#14094000
0#
#14112000
b110000111 '
1#
#14130000
0#
#14148000
b110001000 '
1#
#14166000
0#
#14184000
b110001001 '
1#
#14202000
0#
#14220000
b110001010 '
1#
#14238000
0#
#14256000
b110001011 '
1#
#14274000
0#
#14292000
b110001100 '
1#
#14310000
0#
#14328000
b110001101 '
1#
#14346000
0#
#14364000
b110001110 '
1#
#14382000
0#
#14400000
b110001111 '
1#
#14418000
0#
#14436000
b110010000 '
1#
#14454000
0#
#14472000
b110010001 '
1#
#14490000
0#
#14508000
b110010010 '
1#
#14526000
0#
#14544000
b110010011 '
1#
#14562000
0#
#14580000
b110010100 '
1#
#14598000
0#
#14616000
b110010101 '
1#
#14634000
0#
#14652000
b110010110 '
1#
#14670000
0#
#14688000
b110010111 '
1#
#14706000
0#
#14724000
b110011000 '
1#
#14742000
0#
#14760000
b110011001 '
1#
#14778000
0#
#14796000
b110011010 '
1#
#14814000
0#
#14832000
b110011011 '
1#
#14850000
0#
#14868000
b110011100 '
1#
#14886000
0#
#14904000
b110011101 '
1#
#14922000
0#
#14940000
b110011110 '
1#
#14958000
0#
#14976000
b110011111 '
1#
#14994000
0#
#15012000
b110100000 '
1#
#15030000
0#
#15048000
b110100001 '
1#
#15066000
0#
#15084000
b110100010 '
1#
#15102000
0#
#15120000
b110100011 '
1#
#15138000
0#
#15156000
b110100100 '
1#
#15174000
0#
#15192000
b110100101 '
1#
#15210000
0#
#15228000
b110100110 '
1#
#15246000
0#
#15264000
b110100111 '
1#
#15282000
0#
#15300000
b110101000 '
1#
#15318000
0#
#15336000
b110101001 '
1#
#15354000
0#
#15372000
b110101010 '
1#
#15390000
0#
#15408000
b110101011 '
1#
#15426000
0#
#15444000
b110101100 '
1#
#15462000
0#
#15480000
b110101101 '
1#
#15498000
0#
#15516000
b110101110 '
1#
#15534000
0#
#15552000
b110101111 '
1#
#15570000
0#
#15588000
b110110000 '
1#
#15606000
0#
#15624000
b110110001 '
1#
#15642000
0#
#15660000
b110110010 '
1#
#15678000
0#
#15696000
b110110011 '
1#
#15714000
0#
#15732000
b110110100 '
1#
#15750000
0#
#15768000
b110110101 '
1#
#15786000
0#
#15804000
b110110110 '
1#
#15822000
0#
#15840000
b110110111 '
1#
#15858000
0#
#15876000
b110111000 '
1#
#15894000
0#
#15912000
b110111001 '
1#
#15930000
0#
#15948000
b110111010 '
1#
#15966000
0#
#15984000
b110111011 '
1#
#16002000
0#
#16020000
b110111100 '
1#
#16038000
0#
#16056000
b110111101 '
1#
#16074000
0#
#16092000
b110111110 '
1#
#16110000
0#
#16128000
b110111111 '
1#
#16146000
0#
#16164000
b111000000 '
1#
#16182000
0#
#16200000
b111000001 '
1#
#16218000
0#
#16236000
b111000010 '
1#
#16254000
0#
#16272000
b111000011 '
1#
#16290000
0#
#16308000
b111000100 '
1#
#16326000
0#
#16344000
b111000101 '
1#
#16362000
0#
#16380000
b111000110 '
1#
#16398000
0#
#16416000
b111000111 '
1#
#16434000
0#
#16452000
b111001000 '
1#
#16470000
0#
#16488000
b111001001 '
1#
#16506000
0#
#16524000
b111001010 '
1#
#16542000
0#
#16560000
b111001011 '
1#
#16578000
0#
#16596000
b111001100 '
1#
#16614000
0#
#16632000
b111001101 '
1#
#16650000
0#
#16668000
b111001110 '
1#
#16686000
0#
#16704000
b111001111 '
1#
#16722000
0#
#16740000
b111010000 '
1#
#16758000
0#
#16776000
b111010001 '
1#
#16794000
0#
#16812000
b111010010 '
1#
#16830000
0#
#16848000
b111010011 '
1#
#16866000
0#
#16884000
b111010100 '
1#
#16902000
0#
#16920000
b111010101 '
1#
#16938000
0#
#16956000
b111010110 '
1#
#16974000
0#
#16992000
b111010111 '
1#
#17010000
0#
#17028000
b111011000 '
1#
#17046000
0#
#17064000
b111011001 '
1#
#17082000
0#
#17100000
b111011010 '
1#
#17118000
0#
#17136000
b111011011 '
1#
#17154000
0#
#17172000
b111011100 '
1#
#17190000
0#
#17208000
b111011101 '
1#
#17226000
0#
#17244000
b111011110 '
1#
#17262000
0#
#17280000
b111011111 '
1#
#17298000
0#
#17316000
b111100000 '
1#
#17334000
0#
#17352000
b111100001 '
1#
#17370000
0#
#17388000
b111100010 '
1#
#17406000
0#
#17424000
b111100011 '
1#
#17442000
0#
#17460000
b111100100 '
1#
#17478000
0#
#17496000
b111100101 '
1#
#17514000
0#
#17532000
b111100110 '
1#
#17550000
0#
#17568000
b111100111 '
1#
#17586000
0#
#17604000
b111101000 '
1#
#17622000
0#
#17640000
b111101001 '
1#
#17658000
0#
#17676000
b111101010 '
1#
#17694000
0#
#17712000
b111101011 '
1#
#17730000
0#
#17748000
b111101100 '
1#
#17766000
0#
#17784000
b111101101 '
1#
#17802000
0#
#17820000
b111101110 '
1#
#17838000
0#
#17856000
b111101111 '
1#
#17874000
0#
#17892000
b111110000 '
1#
#17910000
0#
#17928000
b111110001 '
1#
#17946000
0#
#17964000
b111110010 '
1#
#17982000
0#
#18000000
b111110011 '
1#
#18018000
0#
#18036000
b111110100 '
1#
#18054000
0#
#18072000
b111110101 '
1#
#18090000
0#
#18108000
b111110110 '
1#
#18126000
0#
#18144000
b111110111 '
1#
#18162000
0#
#18180000
b111111000 '
1#
#18198000
0#
#18216000
b111111001 '
1#
#18234000
0#
#18252000
b111111010 '
1#
#18270000
0#
#18288000
b111111011 '
1#
#18306000
0#
#18324000
b111111100 '
1#
#18342000
0#
#18360000
b111111101 '
1#
#18378000
0#
#18396000
b111111110 '
1#
#18414000
0#
#18432000
b111111111 '
1#
#18450000
0#
#18468000
b1000000000 '
1#
#18486000
0#
#18504000
b1000000001 '
1#
#18522000
0#
#18540000
b1000000010 '
1#
#18558000
0#
#18576000
b1000000011 '
1#
#18594000
0#
#18612000
b1000000100 '
1#
#18630000
0#
#18648000
b1000000101 '
1#
#18666000
0#
#18684000
b1000000110 '
1#
#18702000
0#
#18720000
b1000000111 '
1#
#18738000
0#
#18756000
b1000001000 '
1#
#18774000
0#
#18792000
b1000001001 '
1#
#18810000
0#
#18828000
b1000001010 '
1#
#18846000
0#
#18864000
b1000001011 '
1#
#18882000
0#
#18900000
b1000001100 '
1#
#18918000
0#
#18936000
b1000001101 '
1#
#18954000
0#
#18972000
b1000001110 '
1#
#18990000
0#
#19008000
b1000001111 '
1#
#19026000
0#
#19044000
b1000010000 '
1#
#19062000
0#
#19080000
b1000010001 '
1#
#19098000
0#
#19116000
b1000010010 '
1#
#19134000
0#
#19152000
b1000010011 '
1#
#19170000
0#
#19188000
b1000010100 '
1#
#19206000
0#
#19224000
b1000010101 '
1#
#19242000
0#
#19260000
b1000010110 '
1#
#19278000
0#
#19296000
b1000010111 '
1#
#19314000
0#
#19332000
b1000011000 '
1#
#19350000
0#
#19368000
b1000011001 '
1#
#19386000
0#
#19404000
b1000011010 '
1#
#19422000
0#
#19440000
b1000011011 '
1#
#19458000
0#
#19476000
b1000011100 '
1#
#19494000
0#
#19512000
b1000011101 '
1#
#19530000
0#
#19548000
b1000011110 '
1#
#19566000
0#
#19584000
b1000011111 '
1#
#19602000
0#
#19620000
b1000100000 '
1#
#19638000
0#
#19656000
b1000100001 '
1#
#19674000
0#
#19692000
b1000100010 '
1#
#19710000
0#
#19728000
b1000100011 '
1#
#19746000
0#
#19764000
b1000100100 '
1#
#19782000
0#
#19800000
b1000100101 '
1#
#19818000
0#
#19836000
b1000100110 '
1#
#19854000
0#
#19872000
b1000100111 '
1#
#19890000
0#
#19908000
b1000101000 '
1#
#19926000
0#
#19944000
b1000101001 '
1#
#19962000
0#
#19980000
b1000101010 '
1#
#19998000
0#
#20016000
b1000101011 '
1#
#20034000
0#
#20052000
b1000101100 '
1#
#20070000
0#
#20088000
b1000101101 '
1#
#20106000
0#
#20124000
b1000101110 '
1#
#20142000
0#
#20160000
b1000101111 '
1#
#20178000
0#
#20196000
b1000110000 '
1#
#20214000
0#
#20232000
b1000110001 '
1#
#20250000
0#
#20268000
b1000110010 '
1#
#20286000
0#
#20304000
b1000110011 '
1#
#20322000
0#
#20340000
b1000110100 '
1#
#20358000
0#
#20376000
b1000110101 '
1#
#20394000
0#
#20412000
b1000110110 '
1#
#20430000
0#
#20448000
b1000110111 '
1#
#20466000
0#
#20484000
b1000111000 '
1#
#20502000
0#
#20520000
b1000111001 '
1#
#20538000
0#
#20556000
b1000111010 '
1#
#20574000
0#
#20592000
b1000111011 '
1#
#20610000
0#
#20628000
b1000111100 '
1#
#20646000
0#
#20664000
b1000111101 '
1#
#20682000
0#
#20700000
b1000111110 '
1#
#20718000
0#
#20736000
b1000111111 '
1#
#20754000
0#
#20772000
b1001000000 '
1#
#20790000
0#
#20808000
b1001000001 '
1#
#20826000
0#
#20844000
b1001000010 '
1#
#20862000
0#
#20880000
b1001000011 '
1#
#20898000
0#
#20916000
b1001000100 '
1#
#20934000
0#
#20952000
b1001000101 '
1#
#20970000
0#
#20988000
b1001000110 '
1#
#21006000
0#
#21024000
b1001000111 '
1#
#21042000
0#
#21060000
b1001001000 '
1#
#21078000
0#
#21096000
b1001001001 '
1#
#21114000
0#
#21132000
b1001001010 '
1#
#21150000
0#
#21168000
b1001001011 '
1#
#21186000
0#
#21204000
b1001001100 '
1#
#21222000
0#
#21240000
b1001001101 '
1#
#21258000
0#
#21276000
b1001001110 '
1#
#21294000
0#
#21312000
b1001001111 '
1#
#21330000
0#
#21348000
b1001010000 '
1#
#21366000
0#
#21384000
b1001010001 '
1#
#21402000
0#
#21420000
b1001010010 '
1#
#21438000
0#
#21456000
b1001010011 '
1#
#21474000
0#
#21492000
b1001010100 '
1#
#21510000
0#
#21528000
b1001010101 '
1#
#21546000
0#
#21564000
b1001010110 '
1#
#21582000
0#
#21600000
b1001010111 '
1#
#21618000
0#
#21636000
b1001011000 '
1#
#21654000
0#
#21672000
b1001011001 '
1#
#21690000
0#
#21708000
b1001011010 '
1#
#21726000
0#
#21744000
b1001011011 '
1#
#21762000
0#
#21780000
b1001011100 '
1#
#21798000
0#
#21816000
b1001011101 '
1#
#21834000
0#
#21852000
b1001011110 '
1#
#21870000
0#
#21888000
b1001011111 '
1#
#21906000
0#
