src/design/module_dato.sv
module module_dato (

    input logic clk,
    input logic rst,
    input logic dato_listo_i,
    input logic [1 : 0] dato_codc_i,
    input logic [1 : 0] dato_codf_i,

    output logic [3 : 0] dato_o //Numero en binario de la tecla presionada
    
);

    logic [3 : 0] pos; //Numero de posicion de la tecla
    logic [3 : 0] dato = 4'd15; 

    always_ff @( posedge clk ) begin 

        if (!rst) begin
            pos <= 4'd14;
        end

        else if (!dato_listo_i) begin
            pos [3 : 2] <= dato_codc_i;
            pos [1 : 0] <= dato_codf_i;
            
        end

        //else if (dato_listo_i) begin
          //  pos  <= 4'd0;
            
            
        //end
    end

    always_comb begin 
        case (pos)
                0 : dato = 4'd1;
                1 : dato = 4'd4;
                2 : dato = 4'd7;
                4 : dato = 4'd2;
                5 : dato = 4'd5;
                6 : dato = 4'd8;
                8 : dato = 4'd3;
                9 : dato = 4'd6;
                10 : dato = 4'd9;
                7 : dato = 4'd0;
                default: dato = 4'd15; // Indica error en la logica secuencial
            endcase
    end
    assign dato_o = dato; //Se niega unicamente para probarlo con los leds de la fpga

endmodule

src/sim/module_dato_tb.sv
`timescale 1ns / 1ps

module module_dato_tb;

    logic clk;
    logic rst;
    logic dato_listo_i;
    logic [1:0] dato_codc_i;
    logic [1:0] dato_codf_i;
    
    logic [3:0] dato_o;

    module_dato uut (
        .clk(clk),
        .rst(rst),
        .dato_listo_i(dato_listo_i),
        .dato_codc_i(dato_codc_i),
        .dato_codf_i(dato_codf_i),
        .dato_o(dato_o)
    );

    // Generación de reloj
    initial begin
        clk = 0;
        forever #5 clk = ~clk; 
    end

    // Proceso de prueba
    initial begin
        $display("Inicio de prueba de module_dato");

        // Inicialización
        rst = 0;
        dato_listo_i = 0;
        dato_codc_i = 2'b00;
        dato_codf_i = 2'b00;
        #10; 
        
        // Liberar reset
        rst = 1;
        #10;

        // Activar dato_listo_i
        dato_listo_i = 1;

        // Comprobación de combinaciones específicas
        // Caso 1: 00 00 -> dato_o debe ser 1
        dato_codc_i = 2'b00;
        dato_codf_i = 2'b00;
        #10;
        $display("dato_codc_i = %b, dato_codf_i = %b, dato_o = %d", dato_codc_i, dato_codf_i, dato_o);

        // Caso 2: 00 01 -> dato_o debe ser 2
        dato_codf_i = 2'b01;
        #10;
        $display("dato_codc_i = %b, dato_codf_i = %b, dato_o = %d", dato_codc_i, dato_codf_i, dato_o);

        // Caso 3: 00 10 -> dato_o debe ser 3
        dato_codf_i = 2'b10;
        #10;
        $display("dato_codc_i = %b, dato_codf_i = %b, dato_o = %d", dato_codc_i, dato_codf_i, dato_o);

        // Caso 4: 00 11 -> dato_o debe ser 15
        dato_codf_i = 2'b11;
        #10;
        $display("dato_codc_i = %b, dato_codf_i = %b, dato_o = %d", dato_codc_i, dato_codf_i, dato_o);

        // Caso 5: 01 00 -> dato_o debe ser 4
        dato_codc_i = 2'b01;
        dato_codf_i = 2'b00;
        #10;
        $display("dato_codc_i = %b, dato_codf_i = %b, dato_o = %d", dato_codc_i, dato_codf_i, dato_o);

        // Caso 6: 01 01 -> dato_o debe ser 5
        dato_codf_i = 2'b01;
        #10;
        $display("dato_codc_i = %b, dato_codf_i = %b, dato_o = %d", dato_codc_i, dato_codf_i, dato_o);

        // Caso 7: 01 10 -> dato_o debe ser 6
        dato_codf_i = 2'b10;
        #10;
        $display("dato_codc_i = %b, dato_codf_i = %b, dato_o = %d", dato_codc_i, dato_codf_i, dato_o);

        // Caso 8: 01 11 -> dato_o debe ser 15
        dato_codf_i = 2'b11;
        #10;
        $display("dato_codc_i = %b, dato_codf_i = %b, dato_o = %d", dato_codc_i, dato_codf_i, dato_o);

        // Caso 9: 10 00 -> dato_o debe ser 7
        dato_codc_i = 2'b10;
        dato_codf_i = 2'b00;
        #10;
        $display("dato_codc_i = %b, dato_codf_i = %b, dato_o = %d", dato_codc_i, dato_codf_i, dato_o);

        // Caso 10: 10 01 -> dato_o debe ser 8
        dato_codf_i = 2'b01;
        #10;
        $display("dato_codc_i = %b, dato_codf_i = %b, dato_o = %d", dato_codc_i, dato_codf_i, dato_o);

        // Caso 11: 10 10 -> dato_o debe ser 9
        dato_codf_i = 2'b10;
        #10;
        $display("dato_codc_i = %b, dato_codf_i = %b, dato_o = %d", dato_codc_i, dato_codf_i, dato_o);

        // Caso 12: 10 11 -> dato_o debe ser 15
        dato_codf_i = 2'b11;
        #10;
        $display("dato_codc_i = %b, dato_codf_i = %b, dato_o = %d", dato_codc_i, dato_codf_i, dato_o);

        //Caso 13: 11 00 -> 15
        dato_codc_i = 2'b11;
        dato_codf_i = 2'b00;
        #10;
        $display("dato_codc_i = %b, dato_codf_i = %b, dato_o = %d", dato_codc_i, dato_codf_i, dato_o);

        //Caso 14: 11 01 -> 0
        dato_codf_i = 2'b01;
        #10;
        $display("dato_codc_i = %b, dato_codf_i = %b, dato_o = %d", dato_codc_i, dato_codf_i, dato_o);

        //Caso 15: 11 10 -> 15
        dato_codf_i = 2'b10;
        #10;
        $display("dato_codc_i = %b, dato_codf_i = %b, dato_o = %d", dato_codc_i, dato_codf_i, dato_o);

        //Caso 16: 11 11 -> 15
        dato_codf_i = 2'b11;
        #10;
        $display("dato_codc_i = %b, dato_codf_i = %b, dato_o = %d", dato_codc_i, dato_codf_i, dato_o);


        // Desactivar dato_listo_i
        dato_listo_i = 0;
        #10;
        $display("Dato no listo nuevamente, dato_o = %d", dato_o);
        
        // Prueba de reset mientras dato_listo_i está activo
        dato_listo_i = 1;
        dato_codc_i = 2'b10; // Caso específico para reset
        dato_codf_i = 2'b01; // Valor de codificación
        #10;
        rst = 0; // Activa reset
        #10;
        rst = 1; // Desactiva reset
        #10;
        
        $display("Fin de prueba de module_dato");
        $finish;
    end

    // Dumps de la simulación para visualización en GTKWAVE
    initial begin
        $dumpfile("module_dato_tb.vcd");
        $dumpvars(0, module_dato_tb);
    end

endmodule

src/build/module_dato_tb.vcd
$date
	Sun Oct 27 22:14:07 2024
$end
$version
	Icarus Verilog
$end
$timescale
	1ps
$end
$scope module module_dato_tb $end
$var wire 4 ! dato_o [3:0] $end
$var reg 1 " clk $end
$var reg 2 # dato_codc_i [1:0] $end
$var reg 2 $ dato_codf_i [1:0] $end
$var reg 1 % dato_listo_i $end
$var reg 1 & rst $end
$scope module uut $end
$var wire 1 " clk $end
$var wire 2 ' dato_codc_i [1:0] $end
$var wire 2 ( dato_codf_i [1:0] $end
$var wire 1 % dato_listo_i $end
$var wire 4 ) dato_o [3:0] $end
$var wire 1 & rst $end
$var reg 4 * dato [3:0] $end
$var reg 4 + pos [3:0] $end
$upscope $end
$upscope $end
$enddefinitions $end
$comment Show the parameter values. $end
$dumpall
$end
#0
$dumpvars
bx +
b1111 *
b1111 )
b0 (
b0 '
0&
0%
b0 $
b0 #
0"
b1111 !
$end
#5000
b1 !
b1 )
b1 *
b0 +
1"
#10000
0"
1&
#15000
1"
#20000
0"
1%
#25000
1"
#30000
0"
b1 $
b1 (
#35000
b10 !
b10 )
b10 *
b1 +
1"
#40000
0"
b10 $
b10 (
#45000
b11 !
b11 )
b11 *
b10 +
1"
#50000
0"
b11 $
b11 (
#55000
b1111 !
b1111 )
b1111 *
b11 +
1"
#60000
0"
b0 $
b0 (
b1 #
b1 '
#65000
b100 !
b100 )
b100 *
b100 +
1"
#70000
0"
b1 $
b1 (
#75000
b101 !
b101 )
b101 *
b101 +
1"
#80000
0"
b10 $
b10 (
#85000
b110 !
b110 )
b110 *
b110 +
1"
#90000
0"
b11 $
b11 (
#95000
b1111 !
b1111 )
b1111 *
b111 +
1"
#100000
0"
b0 $
b0 (
b10 #
b10 '
#105000
b111 !
b111 )
b111 *
b1000 +
1"
#110000
0"
b1 $
b1 (
#115000
b1000 !
b1000 )
b1000 *
b1001 +
1"
#120000
0"
b10 $
b10 (
#125000
b1001 !
b1001 )
b1001 *
b1010 +
1"
#130000
0"
b11 $
b11 (
#135000
b1111 !
b1111 )
b1111 *
b1011 +
1"
#140000
0"
b0 $
b0 (
b11 #
b11 '
#145000
b1100 +
1"
#150000
0"
b1 $
b1 (
#155000
b0 !
b0 )
b0 *
b1101 +
1"
#160000
0"
b10 $
b10 (
#165000
b1111 !
b1111 )
b1111 *
b1110 +
1"
#170000
0"
b11 $
b11 (
#175000
b1111 +
1"
#180000
0"
0%
#185000
1"
#190000
0"
b1 $
b1 (
b10 #
b10 '
1%
#195000
b1000 !
b1000 )
b1000 *
b1001 +
1"
#200000
0"
0&
#205000
b1 !
b1 )
b1 *
b0 +
1"
#210000
0"
1&
#215000
b1000 !
b1000 )
b1000 *
b1001 +
1"
