src/design/module_Debounce.sv
module module_Debounce (
    input logic clk,               
    input logic [3:0] filas_in,    // Entrada de 4 bits (información sobre la fila)
    output logic enable            // Señal de habilitación, activada cuando el dato está estabilizado
);

    // Registro de desplazamiento de 4 bits para almacenar los valores de fila
    logic [3:0][3:0] filas_reg;

    // Proceso secuencial para desplazar los bits de la fila en cada flanco positivo del reloj
    always @(posedge clk) begin
        filas_reg <= {filas_in, filas_reg[3:1]}; // Desplaza los bits
    end

    // Señales auxiliares para almacenar cada bit de filas_reg
    logic filas_reg_3, filas_reg_2, filas_reg_1, filas_reg_0;

    // Asignamos los valores de cada bit de filas_reg a variables auxiliares
    assign filas_reg_3 = filas_reg[3];
    assign filas_reg_2 = filas_reg[2];
    assign filas_reg_1 = filas_reg[1];
    assign filas_reg_0 = filas_reg[0];

    // Lógica combinacional para determinar si la fila está estabilizada
    //always_comb begin
      //  enable = (filas_reg_3 & ~filas_reg_2 & ~filas_reg_1 & ~filas_reg_0); 
    //end

    always_comb begin
    enable = (filas_reg[3] == filas_reg[2]) &&
             (filas_reg[2] == filas_reg[1]) &&
             (filas_reg[1] == filas_reg[0]);
end

endmodule

src/sim/module_DeBounce_tb.sv
`timescale 1 ns / 100 ps

module module_Debounce_tb;

    // Señales de entrada y salida
    logic clk;
    logic [3:0] filas_in;
    logic enable;

    // Instanciación del módulo de debounce
    module_Debounce uut (
        .clk(clk),
        .filas_in(filas_in),
        .enable(enable)
    );

    // Generador de reloj (1 kHz -> 1000 ns por ciclo)
    always #500 clk = ~clk;

    initial begin
        // Inicialización de señales
        clk = 0;
        filas_in = 4'b1111;
        
        // Generación de un rebote en la señal `filas_in`
        // Cambios rápidos de estado para simular ruido de rebote
        #1000 filas_in = 4'b1110;    // Primer cambio
        #1000 filas_in = 4'b1111;    // Vuelve al estado inicial
        #1000 filas_in = 4'b1110;    // Rebote
        #1000 filas_in = 4'b1111;    // Vuelve al estado inicial
        #1000 filas_in = 4'b1110;    // Cambio de nuevo
        #10000 filas_in = 4'b1110;   // Mantiene el estado para estabilizar

        // Después de mantener `filas_in` estable, `enable` debería activarse
        #20000 $finish;                // Fin de la simulación
    end

    // Monitor para observar los cambios en el tiempo
    initial begin
        $monitor("Time=%0t | clk=%b | filas_in=%b | enable=%b",
                 $time, clk, filas_in, enable);
    end

    initial begin
        $dumpfile("module_Debounce_tb.vcd");
        $dumpvars(0, module_Debounce_tb);
    end
endmodule

src/build/module_Debounce_tb.vcd
$date
	Sun Nov 03 21:14:17 2024
$end
$version
	Icarus Verilog
$end
$timescale
	100ps
$end
$scope module module_Debounce_tb $end
$var wire 1 ! enable $end
$var reg 1 " clk $end
$var reg 4 # filas_in [3:0] $end
$scope module uut $end
$var wire 1 " clk $end
$var wire 4 $ filas_in [3:0] $end
$var wire 1 % filas_reg_3 $end
$var wire 1 & filas_reg_2 $end
$var wire 1 ' filas_reg_1 $end
$var wire 1 ( filas_reg_0 $end
$var reg 1 ! enable $end
$var reg 16 ) filas_reg [15:0] $end
$upscope $end
$upscope $end
$enddefinitions $end
$comment Show the parameter values. $end
$dumpall
$end
#0
$dumpvars
bx )
x(
x'
x&
x%
b1111 $
b1111 #
0"
x!
$end
#5000
1%
b1111xxxxxxxxxxxx )
1"
#10000
0"
b1110 #
b1110 $
#15000
0%
1&
0!
b11101111xxxxxxxx )
1"
#20000
0"
b1111 #
b1111 $
#25000
1%
0&
1'
b111111101111xxxx )
1"
#30000
0"
b1110 #
b1110 $
#35000
0%
1&
0'
1(
b1110111111101111 )
1"
#40000
0"
b1111 #
b1111 $
#45000
1%
0&
1'
0(
b1111111011111110 )
1"
#50000
0"
b1110 #
b1110 $
#55000
0%
1&
0'
1(
b1110111111101111 )
1"
#60000
0"
#65000
0&
1'
0(
b1110111011111110 )
1"
#70000
0"
#75000
0'
1(
b1110111011101111 )
1"
#80000
0"
#85000
0(
1!
b1110111011101110 )
1"
