src/design/module_keypress.sv
module module_keypress (

    input logic [1 : 0] dato_codc_i,
    input logic [3 : 0] posf_i, //Nota mental: definir en los constr

    output logic [1 : 0] dato_codf_o 
);

logic [3 : 0] column; //Nota mental: definir en los constr
logic [1 : 0] fila;

always_comb begin 

    case (dato_codc_i) 
        2'b00 : column = 4'b1110;
        2'b01 : column = 4'b1101;
        2'b10 : column = 4'b1011;
        2'b11 : column = 4'b0111; 
        default: column = 4'b1110;
    endcase

end

always_comb begin 
    
    case (posf_i)
        4'b1110 : fila = 2'b00;
        4'b1101 : fila = 2'b01;
        4'b1011 : fila = 2'b10;
        4'b0111 : fila = 2'b11;
        default: fila = 2'b00; 
    endcase
end

assign dato_codf_o = fila;

endmodule

src/sim/module_keypress_tb.sv
`timescale 1ns/1ps

module module_keypress_tb;

    logic [1 : 0] dato_codc_i;
    logic [3 : 0] posf_i;
    logic [1 : 0] dato_codf_o;
    
    module_keypress uut (
        .dato_codc_i(dato_codc_i),
        .posf_i(posf_i),
        .dato_codf_o(dato_codf_o)
    );

    initial begin
        $monitor("Time=%0t | dato_codc_i=%b | posf_i=%b | dato_codf_o=%b", 
                 $time, dato_codc_i, posf_i, dato_codf_o);

        // Prueba para cada valor de dato_codc_i con los valores válidos de posf_i
        for (int i = 0; i < 4; i++) begin
            dato_codc_i = i[1:0];
            #10 posf_i = 4'b1111; #10;
            #10 posf_i = 4'b1110; #10;
            #10 posf_i = 4'b1101; #10;
            #10 posf_i = 4'b1011; #10;
            #10 posf_i = 4'b0111; #10;
        end
        
        // Prueba del caso por defecto
        dato_codc_i = 2'b10; 
        posf_i = 4'b0000; 
        #10;
        
        $finish;
    end

    // Dumps para visualización en GTKWAVE
    initial begin
        $dumpfile("module_keypress_tb.vcd");
        $dumpvars(0, module_keypress_tb);
    end

endmodule

src/build/module_keypress_tb.vcd
$date
	Fri Oct 25 18:58:53 2024
$end
$version
	Icarus Verilog
$end
$timescale
	1ps
$end
$scope module module_keypress_tb $end
$var wire 2 ! dato_codf_o [1:0] $end
$var reg 2 " dato_codc_i [1:0] $end
$var reg 4 # posf_i [3:0] $end
$scope module uut $end
$var wire 2 $ dato_codc_i [1:0] $end
$var wire 2 % dato_codf_o [1:0] $end
$var wire 4 & posf_i [3:0] $end
$var reg 4 ' column [3:0] $end
$var reg 2 ( fila [1:0] $end
$upscope $end
$scope begin $ivl_for_loop0 $end
$var integer 32 ) i [31:0] $end
$upscope $end
$upscope $end
$enddefinitions $end
$comment Show the parameter values. $end
$dumpall
$end
#0
$dumpvars
b0 )
b0 (
b1110 '
bx &
b0 %
b0 $
bx #
b0 "
b0 !
$end
#10000
b1111 #
b1111 &
#30000
b1110 #
b1110 &
#50000
b1 !
b1 %
b1 (
b1101 #
b1101 &
#70000
b10 !
b10 %
b10 (
b1011 #
b1011 &
#90000
b11 !
b11 %
b11 (
b111 #
b111 &
#100000
b1101 '
b1 "
b1 $
b1 )
#110000
b0 !
b0 %
b0 (
b1111 #
b1111 &
#130000
b1110 #
b1110 &
#150000
b1 !
b1 %
b1 (
b1101 #
b1101 &
#170000
b10 !
b10 %
b10 (
b1011 #
b1011 &
#190000
b11 !
b11 %
b11 (
b111 #
b111 &
#200000
b1011 '
b10 "
b10 $
b10 )
#210000
b0 !
b0 %
b0 (
b1111 #
b1111 &
#230000
b1110 #
b1110 &
#250000
b1 !
b1 %
b1 (
b1101 #
b1101 &
#270000
b10 !
b10 %
b10 (
b1011 #
b1011 &
#290000
b11 !
b11 %
b11 (
b111 #
b111 &
#300000
b11 "
b11 $
b11 )
#310000
b0 !
b0 %
b0 (
b1111 #
b1111 &
#330000
b1110 #
b1110 &
#350000
b1 !
b1 %
b1 (
b1101 #
b1101 &
#370000
b10 !
b10 %
b10 (
b1011 #
b1011 &
#390000
b11 !
b11 %
b11 (
b111 #
b111 &
#400000
b0 !
b0 %
b0 (
b0 #
b0 &
b10 "
b10 $
b100 )
