src/design/sign_magnitude.sv
module sign_magnitude(
    input logic clk, reset, valid,
    input logic [15 : 0] mult_result,
    output logic [15 : 0] magnitude,
    output logic sign, mult_sign_magnitude_ready
);
    logic mult_sign;
    logic [15 : 0] mult_magnitude;

    always_ff @(posedge clk or posedge reset) begin
        if(reset) begin
            mult_sign <= 0;
            mult_magnitude <= 0;
            mult_sign_magnitude_ready <= 0;

        end else if(valid) begin
            mult_sign <= mult_result[15];

            if(mult_sign) begin
                mult_magnitude <= {1'b0, (~mult_result[14 : 0]) + 15'b1};

            end else begin
                mult_magnitude <= mult_result;
            end

            mult_sign_magnitude_ready <= 1;
        end
    end

    assign magnitude = mult_magnitude;
    assign sign = mult_sign;
endmodule

src/sim/sign_magnitude_tb.sv
module sign_magnitude_tb;

    // Señales para instanciar el módulo sign_magnitude
    logic clk, reset, valid;
    logic [15:0] mult_result;
    logic [15:0] magnitude;
    logic sign, mult_sign_magnitude_ready;

    // Instanciar el módulo sign_magnitude
    sign_magnitude uut (
        .clk(clk),
        .reset(reset),
        .valid(valid),
        .mult_result(mult_result),
        .magnitude(magnitude),
        .sign(sign),
        .mult_sign_magnitude_ready(mult_sign_magnitude_ready)
    );

    // Generar señal de reloj
    always #5 clk = ~clk;

    // Procedimiento de prueba
    initial begin
        // Iniciar el archivo .vcd para volcar señales
        $dumpfile("tb_sign_magnitude.vcd");
        $dumpvars(0, sign_magnitude_tb);
        
        // Inicializar señales
        clk = 0;
        reset = 1;
        valid = 0;
        mult_result = 16'h0000;
        
        // Soltar el reset después de un ciclo de reloj
        #10 
        reset = 1;
        valid = 0;
        #10
        reset = 0;

        // Test 1: Número negativo (-0x1234 en complemento a dos)
        #10 mult_result = 16'b1111101100100000;  // -4660 en complemento a dos
        #10 valid = 1;
        #20 $display("Test 1: mult_result = %0d, magnitude = %0d, sign = %b", $signed(mult_result), magnitude, sign);

        // Test 2: Número positivo (0x207C)
        #10 
        reset = 1;
        valid = 0;
        #10
        reset = 0;
        #10 mult_result = 16'b0010000001111100;  // 8316 en decimal
        #10 valid = 1;
        #20 $display("Test 2: mult_result = %0d, magnitude = %0d, sign = %b", $signed(mult_result), magnitude, sign);

        // Test 3: Otro número negativo
        #10 
        reset = 1;
        valid = 0;
        #10
        reset = 0;
        #10 mult_result = 16'b1101100110110111;  // -9801 en complemento a dos
        #10 valid = 1;
        #20 $display("Test 3: mult_result = %0d, magnitude = %0d, sign = %b", $signed(mult_result), magnitude, sign);

        // Test 4: Número positivo pequeño
        #10 
        reset = 1;
        valid = 0;
        #10
        reset = 0;
        #10 mult_result = 16'b0000000001011001;  // 89 en decimal
        #10 valid = 1;
        #20 $display("Test 4: mult_result = %0d, magnitude = %0d, sign = %b", $signed(mult_result), magnitude, sign);

        // Finalizar la simulación
        #30 $finish;
    end

endmodule

src/build/tb_sign_magnitude.vcd
$date
	Wed Nov 06 16:49:09 2024
$end
$version
	Icarus Verilog
$end
$timescale
	1s
$end
$scope module sign_magnitude_tb $end
$var wire 1 ! sign $end
$var wire 1 " mult_sign_magnitude_ready $end
$var wire 16 # magnitude [15:0] $end
$var reg 1 $ clk $end
$var reg 16 % mult_result [15:0] $end
$var reg 1 & reset $end
$var reg 1 ' valid $end
$scope module uut $end
$var wire 1 $ clk $end
$var wire 16 ( magnitude [15:0] $end
$var wire 16 ) mult_result [15:0] $end
$var wire 1 & reset $end
$var wire 1 ! sign $end
$var wire 1 ' valid $end
$var reg 16 * mult_magnitude [15:0] $end
$var reg 1 + mult_sign $end
$var reg 1 " mult_sign_magnitude_ready $end
$upscope $end
$upscope $end
$enddefinitions $end
$comment Show the parameter values. $end
$dumpall
$end
#0
$dumpvars
0+
b0 *
b0 )
b0 (
0'
1&
b0 %
0$
b0 #
0"
0!
$end
#5
1$
#10
0$
#15
1$
#20
0$
0&
#25
1$
#30
0$
b1111101100100000 %
b1111101100100000 )
#35
1$
#40
0$
1'
#45
1"
b1111101100100000 #
b1111101100100000 (
b1111101100100000 *
1!
1+
1$
#50
0$
#55
b10011100000 #
b10011100000 (
b10011100000 *
1$
#60
0$
#65
1$
#70
0"
b0 #
b0 (
b0 *
0!
0+
0$
0'
1&
#75
1$
#80
0$
0&
#85
1$
#90
0$
b10000001111100 %
b10000001111100 )
#95
1$
#100
0$
1'
#105
1"
b10000001111100 #
b10000001111100 (
b10000001111100 *
1$
#110
0$
#115
1$
#120
0$
#125
1$
#130
0"
b0 #
b0 (
b0 *
0$
0'
1&
#135
1$
#140
0$
0&
#145
1$
#150
0$
b1101100110110111 %
b1101100110110111 )
#155
1$
#160
0$
1'
#165
1"
b1101100110110111 #
b1101100110110111 (
b1101100110110111 *
1!
1+
1$
#170
0$
#175
b10011001001001 #
b10011001001001 (
b10011001001001 *
1$
#180
0$
#185
1$
#190
0"
b0 #
b0 (
b0 *
0!
0+
0$
0'
1&
#195
1$
#200
0$
0&
#205
1$
#210
0$
b1011001 %
b1011001 )
#215
1$
#220
0$
1'
#225
1"
b1011001 #
b1011001 (
b1011001 *
1$
