src/design/module_dato.sv
module module_dato (

    input logic clk,
    input logic rst,
    input logic dato_listo_i,
    input logic [1 : 0] dato_codc_i,
    input logic [1 : 0] dato_codf_i,

    output logic [3 : 0] dato_o //Numero en binario de la tecla presionada
    
);

    logic [3 : 0] pos; //Numero de posicion de la tecla
    logic [3 : 0] dato = 4'd15; 

    always_ff @( posedge clk ) begin 

        if (!rst) begin
            pos <= 4'd14;
        end

        else if (dato_listo_i) begin
            pos [3 : 2] <= dato_codc_i;
            pos [1 : 0] <= dato_codf_i;
            
        end
    end

    always_comb begin 
        case (pos)
                0 : dato = 4'd1;
                1 : dato = 4'd4;
                2 : dato = 4'd7;
                4 : dato = 4'd2;
                5 : dato = 4'd5;
                6 : dato = 4'd8;
                8 : dato = 4'd3;
                9 : dato = 4'd6;
                10 : dato = 4'd9;
                7 : dato = 4'd0;
                default: dato = 4'd15; // Indica error en la logica secuencial
            endcase
    end
    assign dato_o = ~dato; //Se niega unicamente para probarlo con los leds de la fpga

endmodule

src/design/module_Debounce.sv
module module_Debounce (
    input logic clk,               
    input logic [3:0] filas_in,    // Entrada de 4 bits (información sobre la fila)
    output logic enable            // Señal de habilitación, activada cuando el dato está estabilizado
);

    // Registro de desplazamiento de 4 bits para almacenar los valores de fila
    logic [3:0][3:0] filas_reg;

    // Proceso secuencial para desplazar los bits de la fila en cada flanco positivo del reloj
    always @(posedge clk) begin
        filas_reg <= {filas_in, filas_reg[3:1]}; // Desplaza los bits
    end

    // Señales auxiliares para almacenar cada bit de filas_reg
    logic filas_reg_3, filas_reg_2, filas_reg_1, filas_reg_0;

    // Asignamos los valores de cada bit de filas_reg a variables auxiliares
    assign filas_reg_3 = filas_reg[3];
    assign filas_reg_2 = filas_reg[2];
    assign filas_reg_1 = filas_reg[1];
    assign filas_reg_0 = filas_reg[0];

    // Lógica combinacional para determinar si la fila está estabilizada
    //always_comb begin
      //  enable = (filas_reg_3 & ~filas_reg_2 & ~filas_reg_1 & ~filas_reg_0); 
    //end

    always_comb begin
    enable = (filas_reg[3] == filas_reg[2]) &&
             (filas_reg[2] == filas_reg[1]) &&
             (filas_reg[1] == filas_reg[0]);
end

endmodule

src/design/module_keypress.sv
module module_keypress (

    input logic [1 : 0] dato_codc_i,
    input logic [3 : 0] posf_i, //Nota mental: definir en los constr

    output logic [1 : 0] dato_codf_o,
    output logic [3 : 0] columna_o  //Nota mental: definir en los constr
);

logic [3 : 0] column;
logic [1 : 0] fila;

always_comb begin 

    case (dato_codc_i) 
        2'b00 : column = 4'b1110;
        2'b01 : column = 4'b1101;
        2'b10 : column = 4'b1011;
        2'b11 : column = 4'b0111; 
        default: column = 4'b1110;
    endcase

end

always_comb begin 
    
    case (posf_i)
        4'b1110 : fila = 2'b00;
        4'b1101 : fila = 2'b01;
        4'b1011 : fila = 2'b10;
        4'b0111 : fila = 2'b11;
        default: fila = 2'b00; 
    endcase
end

assign dato_codf_o = fila;
assign columna_o = column;

endmodule

src/design/module_cont_2b.sv
// ------------Tecnológico de Costa Rica-----------
// Escuela de Ingeniería Electrónica: Diseño Lógico

// Subsistema de captura de datos
// Pablo Elizondo Espinoza
// Eduardo Tencio Solano
// Karina Quiros Avila

module module_cont_2b (

    input logic clk,
    input logic rst,
    input logic stop,

    output logic [1 : 0] cont_out //contador de 2 bits
);

    logic [1 : 0] cont = 0;
    
    always_ff @( posedge clk ) begin 

        if (!rst) begin
            cont <= 0;
        end

        else if (cont == 3) begin
            cont <= 0;
        end
        
        else if (stop) begin
            cont <= cont + 1;
        end

        else if (!stop) begin
            cont <= cont;
        end

    end

    assign cont_out = cont;

endmodule

src/design/module_divisor.sv
module module_divisor # (

    parameter COUNT = 13500 

) (

    input logic clk,
    input logic rst,

    output logic prd_out //periodo salida
);

    localparam WIDTH_COUNT = $clog2(COUNT); //Cantidad de bits para representar el numero
    
    logic [WIDTH_COUNT - 1 : 0] clk_counter = 0;//Contador
    logic prd_new = 0;

    always_ff @( posedge clk ) begin 
        
        if (!rst) begin
            prd_new <= 0;
            clk_counter <= 0;
        end

        else if (clk_counter == COUNT -1) begin
            prd_new <= ~prd_new;
            clk_counter <= 0;
        end

        else begin
            clk_counter <= clk_counter + 1;
        end
    end

    assign prd_out = prd_new;

endmodule

src/design/Top_module.sv
`timescale 1 ns / 100 ps

module Top_module (
    input logic clk,               // Reloj principal
    input logic rst,               // Reset global
    input logic [3:0] key_in,      // Entrada del teclado sin debounce

    output logic data_available,    // Señal que indica que el dato está listo
    output logic [3 : 0] columna_o, //Señal barrido de columnas 
    output logic [3:0] dato_o     // Valor binario de la tecla presionada
    
);

    // Señales internas para conexiones entre módulos
    logic prd_out;                // Salida del divisor de frecuencia
    logic [1:0] dato_codc;        // Salida codificada de columna y salida del contador de 2 bits
    logic [1:0] dato_codf;        // Salida codificada de fila

    // Instancia del divisor de frecuencia
    module_divisor #(.COUNT(13500)) divisor (
        .clk(clk),
        .rst(rst),
        .prd_out(prd_out)
    );

    module_cont_2b contador (
        .clk (prd_out),
        .rst (rst),
        .stop (data_available),
        .cont_out(dato_codc)
    );

    module_keypress keypress (
        .dato_codc_i (dato_codc),
        .posf_i (key_in),
        .dato_codf_o (dato_codf),
        .columna_o (columna_o)
    );

    module_Debounce debounce (
        .clk (clk),
        .filas_in (key_in),
        .enable (data_available)
    );

    module_dato dato (
        .clk (clk),
        .rst (rst),
        .dato_listo_i (data_available),
        .dato_codc_i (dato_codc),
        .dato_codf_i (dato_codf),
        .dato_o (dato_o)
    );

endmodule

src/sim/Top_module_teclado_tb.sv
`timescale 1 ns / 100 ps

module Top_module_tb;

    // Señales de testbench
    logic clk;
    logic rst;
    logic [3:0] key_in;

    logic data_available;
    logic [3:0] dato_o;
    
    // Instancia del módulo `Top_module`
    Top_module DUT (
        .clk(clk),
        .rst(rst),
        .key_in(key_in),
        .data_available(data_available),
        .dato_o(dato_o)
    );

    // Generación de reloj principal a 27 MHz
    initial begin
        clk = 0;
        forever #18.5 clk = ~clk;  // Periodo de 37 ns (aprox. 27 MHz)
    end

    // Proceso de simulación
    initial begin
        // Inicialización
        rst = 0;
        key_in = 4'b1111; // Sin teclas presionadas al inicio
        
        // Activación de reset
        #100 rst = 1;
        
        // Simulación de presiones de teclas en `key_in`
        repeat (3) begin
            // Primera tecla presionada - Fila 1
            key_in = 4'b1110;  // Simula la activación de la fila 1
            #200000;            // Espera de tiempo para procesar

            // Segunda tecla presionada - Fila 2
            key_in = 4'b1101;  // Simula la activación de la fila 2
            #200000;

            // Tercera tecla presionada - Fila 3
            key_in = 4'b1011;  // Simula la activación de la fila 3
            #200000;

            // Cuarta tecla presionada - Fila 4
            key_in = 4'b0111;  // Simula la activación de la fila 4
            #200000;

            // Regresar a sin teclas presionadas
            key_in = 4'b1111;
            #50000;  // Pausa entre ciclos
        end

        // Finalizar simulación
        $finish;
    end

    // Monitoreo de salidas
    initial begin
        $monitor("Time=%0t | rst=%b | key_in=%b | data_available=%b | dato_o=%h",
                 $time, rst, key_in, data_available, dato_o);
    end

    initial begin
        $dumpfile("Top_module_tb.vcd");
        $dumpvars(0, Top_module_tb);
    end

endmodule

src/build/Top_module_tb.vcd
$date
	Wed Nov 06 16:13:27 2024
$end
$version
	Icarus Verilog
$end
$timescale
	100ps
$end
$scope module Top_module_tb $end
$var wire 4 ! dato_o [3:0] $end
$var wire 1 " data_available $end
$var reg 1 # clk $end
$var reg 4 $ key_in [3:0] $end
$var reg 1 % rst $end
$scope module DUT $end
$var wire 1 # clk $end
$var wire 4 & key_in [3:0] $end
$var wire 1 % rst $end
$var wire 1 ' prd_out $end
$var wire 4 ( dato_o [3:0] $end
$var wire 2 ) dato_codf [1:0] $end
$var wire 2 * dato_codc [1:0] $end
$var wire 1 " data_available $end
$var wire 4 + columna_o [3:0] $end
$scope module contador $end
$var wire 2 , cont_out [1:0] $end
$var wire 1 % rst $end
$var wire 1 " stop $end
$var wire 1 ' clk $end
$var reg 2 - cont [1:0] $end
$upscope $end
$scope module dato $end
$var wire 1 # clk $end
$var wire 2 . dato_codc_i [1:0] $end
$var wire 4 / dato_o [3:0] $end
$var wire 1 % rst $end
$var wire 1 " dato_listo_i $end
$var wire 2 0 dato_codf_i [1:0] $end
$var reg 4 1 dato [3:0] $end
$var reg 4 2 pos [3:0] $end
$upscope $end
$scope module debounce $end
$var wire 1 # clk $end
$var wire 4 3 filas_in [3:0] $end
$var wire 1 4 filas_reg_3 $end
$var wire 1 5 filas_reg_2 $end
$var wire 1 6 filas_reg_1 $end
$var wire 1 7 filas_reg_0 $end
$var reg 1 " enable $end
$var reg 16 8 filas_reg [15:0] $end
$upscope $end
$scope module divisor $end
$var wire 1 # clk $end
$var wire 1 ' prd_out $end
$var wire 1 % rst $end
$var parameter 32 9 COUNT $end
$var parameter 32 : WIDTH_COUNT $end
$var reg 14 ; clk_counter [13:0] $end
$var reg 1 < prd_new $end
$upscope $end
$scope module keypress $end
$var wire 4 = columna_o [3:0] $end
$var wire 2 > dato_codc_i [1:0] $end
$var wire 2 ? dato_codf_o [1:0] $end
$var wire 4 @ posf_i [3:0] $end
$var reg 4 A column [3:0] $end
$var reg 2 B fila [1:0] $end
$upscope $end
$upscope $end
$upscope $end
$enddefinitions $end
$comment Show the parameter values. $end
$dumpall
b1110 :
b11010010111100 9
$end
#0
$dumpvars
b0 B
b1110 A
b1111 @
b0 ?
b0 >
b1110 =
0<
b0 ;
bx 8
x7
x6
x5
x4
b1111 3
bx 2
b1111 1
b0 0
b1111 /
b0 .
b0 -
b0 ,
b1110 +
b0 *
b0 )
b1111 (
0'
b1111 &
0%
b1111 $
0#
x"
b1111 !
$end
#185
14
b1111xxxxxxxxxxxx 8
b1110 2
1#
#370
0#
#555
15
b11111111xxxxxxxx 8
1#
#740
0#
#925
16
b111111111111xxxx 8
1#
#1000
b1110 $
b1110 &
b1110 3
b1110 @
1%
#1110
0#
#1295
04
17
0"
b1110111111111111 8
b1 ;
1#
#1480
0#
#1665
05
b10 ;
b1110111011111111 8
1#
#1850
0#
#2035
06
b1110111011101111 8
b11 ;
1#
#2220
0#
#2405
07
1"
b100 ;
b1110111011101110 8
1#
#2590
0#
#2775
b1 !
b1 (
b1 /
b1 1
b0 2
b101 ;
1#
#2960
0#
#3145
b110 ;
1#
#3330
0#
#3515
b111 ;
1#
#3700
0#
#3885
b1000 ;
1#
#4070
0#
#4255
b1001 ;
1#
#4440
0#
#4625
b1010 ;
1#
#4810
0#
#4995
b1011 ;
1#
#5180
0#
#5365
b1100 ;
1#
#5550
0#
#5735
b1101 ;
1#
#5920
0#
#6105
b1110 ;
1#
#6290
0#
#6475
b1111 ;
1#
#6660
0#
#6845
b10000 ;
1#
#7030
0#
#7215
b10001 ;
1#
#7400
0#
#7585
b10010 ;
1#
#7770
0#
#7955
b10011 ;
1#
#8140
0#
#8325
b10100 ;
1#
#8510
0#
#8695
b10101 ;
1#
#8880
0#
#9065
b10110 ;
1#
#9250
0#
#9435
b10111 ;
1#
#9620
0#
#9805
b11000 ;
1#
#9990
0#
#10175
b11001 ;
1#
#10360
0#
#10545
b11010 ;
1#
#10730
0#
#10915
b11011 ;
1#
#11100
0#
#11285
b11100 ;
1#
#11470
0#
#11655
b11101 ;
1#
#11840
0#
#12025
b11110 ;
1#
#12210
0#
#12395
b11111 ;
1#
#12580
0#
#12765
b100000 ;
1#
#12950
0#
#13135
b100001 ;
1#
#13320
0#
#13505
b100010 ;
1#
#13690
0#
#13875
b100011 ;
1#
#14060
0#
#14245
b100100 ;
1#
#14430
0#
#14615
b100101 ;
1#
#14800
0#
#14985
b100110 ;
1#
#15170
0#
#15355
b100111 ;
1#
#15540
0#
#15725
b101000 ;
1#
#15910
0#
#16095
b101001 ;
1#
#16280
0#
#16465
b101010 ;
1#
#16650
0#
#16835
b101011 ;
1#
#17020
0#
#17205
b101100 ;
1#
#17390
0#
#17575
b101101 ;
1#
#17760
0#
#17945
b101110 ;
1#
#18130
0#
#18315
b101111 ;
1#
#18500
0#
#18685
b110000 ;
1#
#18870
0#
#19055
b110001 ;
1#
#19240
0#
#19425
b110010 ;
1#
#19610
0#
#19795
b110011 ;
1#
#19980
0#
#20165
b110100 ;
1#
#20350
0#
#20535
b110101 ;
1#
#20720
0#
#20905
b110110 ;
1#
#21090
0#
#21275
b110111 ;
1#
#21460
0#
#21645
b111000 ;
1#
#21830
0#
#22015
b111001 ;
1#
#22200
0#
#22385
b111010 ;
1#
#22570
0#
#22755
b111011 ;
1#
#22940
0#
#23125
b111100 ;
1#
#23310
0#
#23495
b111101 ;
1#
#23680
0#
#23865
b111110 ;
1#
#24050
0#
#24235
b111111 ;
1#
#24420
0#
#24605
b1000000 ;
1#
#24790
0#
#24975
b1000001 ;
1#
#25160
0#
#25345
b1000010 ;
1#
#25530
0#
#25715
b1000011 ;
1#
#25900
0#
#26085
b1000100 ;
1#
#26270
0#
#26455
b1000101 ;
1#
#26640
0#
#26825
b1000110 ;
1#
#27010
0#
#27195
b1000111 ;
1#
#27380
0#
#27565
b1001000 ;
1#
#27750
0#
#27935
b1001001 ;
1#
#28120
0#
#28305
b1001010 ;
1#
#28490
0#
#28675
b1001011 ;
1#
#28860
0#
#29045
b1001100 ;
1#
#29230
0#
#29415
b1001101 ;
1#
#29600
0#
#29785
b1001110 ;
1#
#29970
0#
#30155
b1001111 ;
1#
#30340
0#
#30525
b1010000 ;
1#
#30710
0#
#30895
b1010001 ;
1#
#31080
0#
#31265
b1010010 ;
1#
#31450
0#
#31635
b1010011 ;
1#
#31820
0#
#32005
b1010100 ;
1#
#32190
0#
#32375
b1010101 ;
1#
#32560
0#
#32745
b1010110 ;
1#
#32930
0#
#33115
b1010111 ;
1#
#33300
0#
#33485
b1011000 ;
1#
#33670
0#
#33855
b1011001 ;
1#
#34040
0#
#34225
b1011010 ;
1#
#34410
0#
#34595
b1011011 ;
1#
#34780
0#
#34965
b1011100 ;
1#
#35150
0#
#35335
b1011101 ;
1#
#35520
0#
#35705
b1011110 ;
1#
#35890
0#
#36075
b1011111 ;
1#
#36260
0#
#36445
b1100000 ;
1#
#36630
0#
#36815
b1100001 ;
1#
#37000
0#
#37185
b1100010 ;
1#
#37370
0#
#37555
b1100011 ;
1#
#37740
0#
#37925
b1100100 ;
1#
#38110
0#
#38295
b1100101 ;
1#
#38480
0#
#38665
b1100110 ;
1#
#38850
0#
#39035
b1100111 ;
1#
#39220
0#
#39405
b1101000 ;
1#
#39590
0#
#39775
b1101001 ;
1#
#39960
0#
#40145
b1101010 ;
1#
#40330
0#
#40515
b1101011 ;
1#
#40700
0#
#40885
b1101100 ;
1#
#41070
0#
#41255
b1101101 ;
1#
#41440
0#
#41625
b1101110 ;
1#
#41810
0#
#41995
b1101111 ;
1#
#42180
0#
#42365
b1110000 ;
1#
#42550
0#
#42735
b1110001 ;
1#
#42920
0#
#43105
b1110010 ;
1#
#43290
0#
#43475
b1110011 ;
1#
#43660
0#
#43845
b1110100 ;
1#
#44030
0#
#44215
b1110101 ;
1#
#44400
0#
#44585
b1110110 ;
1#
#44770
0#
#44955
b1110111 ;
1#
#45140
0#
#45325
b1111000 ;
1#
#45510
0#
#45695
b1111001 ;
1#
#45880
0#
#46065
b1111010 ;
1#
#46250
0#
#46435
b1111011 ;
1#
#46620
0#
#46805
b1111100 ;
1#
#46990
0#
#47175
b1111101 ;
1#
#47360
0#
#47545
b1111110 ;
1#
#47730
0#
#47915
b1111111 ;
1#
#48100
0#
#48285
b10000000 ;
1#
#48470
0#
#48655
b10000001 ;
1#
#48840
0#
#49025
b10000010 ;
1#
#49210
0#
#49395
b10000011 ;
1#
#49580
0#
#49765
b10000100 ;
1#
#49950
0#
#50135
b10000101 ;
1#
#50320
0#
#50505
b10000110 ;
1#
#50690
0#
#50875
b10000111 ;
1#
#51060
0#
#51245
b10001000 ;
1#
#51430
0#
#51615
b10001001 ;
1#
#51800
0#
#51985
b10001010 ;
1#
#52170
0#
#52355
b10001011 ;
1#
#52540
0#
#52725
b10001100 ;
1#
#52910
0#
#53095
b10001101 ;
1#
#53280
0#
#53465
b10001110 ;
1#
#53650
0#
#53835
b10001111 ;
1#
#54020
0#
#54205
b10010000 ;
1#
#54390
0#
#54575
b10010001 ;
1#
#54760
0#
#54945
b10010010 ;
1#
#55130
0#
#55315
b10010011 ;
1#
#55500
0#
#55685
b10010100 ;
1#
#55870
0#
#56055
b10010101 ;
1#
#56240
0#
#56425
b10010110 ;
1#
#56610
0#
#56795
b10010111 ;
1#
#56980
0#
#57165
b10011000 ;
1#
#57350
0#
#57535
b10011001 ;
1#
#57720
0#
#57905
b10011010 ;
1#
#58090
0#
#58275
b10011011 ;
1#
#58460
0#
#58645
b10011100 ;
1#
#58830
0#
#59015
b10011101 ;
1#
#59200
0#
#59385
b10011110 ;
1#
#59570
0#
#59755
b10011111 ;
1#
#59940
0#
#60125
b10100000 ;
1#
#60310
0#
#60495
b10100001 ;
1#
#60680
0#
#60865
b10100010 ;
1#
#61050
0#
#61235
b10100011 ;
1#
#61420
0#
#61605
b10100100 ;
1#
#61790
0#
#61975
b10100101 ;
1#
#62160
0#
#62345
b10100110 ;
1#
#62530
0#
#62715
b10100111 ;
1#
#62900
0#
#63085
b10101000 ;
1#
#63270
0#
#63455
b10101001 ;
1#
#63640
0#
#63825
b10101010 ;
1#
#64010
0#
#64195
b10101011 ;
1#
#64380
0#
#64565
b10101100 ;
1#
#64750
0#
#64935
b10101101 ;
1#
#65120
0#
#65305
b10101110 ;
1#
#65490
0#
#65675
b10101111 ;
1#
#65860
0#
#66045
b10110000 ;
1#
#66230
0#
#66415
b10110001 ;
1#
#66600
0#
#66785
b10110010 ;
1#
#66970
0#
#67155
b10110011 ;
1#
#67340
0#
#67525
b10110100 ;
1#
#67710
0#
#67895
b10110101 ;
1#
#68080
0#
#68265
b10110110 ;
1#
#68450
0#
#68635
b10110111 ;
1#
#68820
0#
#69005
b10111000 ;
1#
#69190
0#
#69375
b10111001 ;
1#
#69560
0#
#69745
b10111010 ;
1#
#69930
0#
#70115
b10111011 ;
1#
#70300
0#
#70485
b10111100 ;
1#
#70670
0#
#70855
b10111101 ;
1#
#71040
0#
#71225
b10111110 ;
1#
#71410
0#
#71595
b10111111 ;
1#
#71780
0#
#71965
b11000000 ;
1#
#72150
0#
#72335
b11000001 ;
1#
#72520
0#
#72705
b11000010 ;
1#
#72890
0#
#73075
b11000011 ;
1#
#73260
0#
#73445
b11000100 ;
1#
#73630
0#
#73815
b11000101 ;
1#
#74000
0#
#74185
b11000110 ;
1#
#74370
0#
#74555
b11000111 ;
1#
#74740
0#
#74925
b11001000 ;
1#
#75110
0#
#75295
b11001001 ;
1#
#75480
0#
#75665
b11001010 ;
1#
#75850
0#
#76035
b11001011 ;
1#
#76220
0#
#76405
b11001100 ;
1#
#76590
0#
#76775
b11001101 ;
1#
#76960
0#
#77145
b11001110 ;
1#
#77330
0#
#77515
b11001111 ;
1#
#77700
0#
#77885
b11010000 ;
1#
#78070
0#
#78255
b11010001 ;
1#
#78440
0#
#78625
b11010010 ;
1#
#78810
0#
#78995
b11010011 ;
1#
#79180
0#
#79365
b11010100 ;
1#
#79550
0#
#79735
b11010101 ;
1#
#79920
0#
#80105
b11010110 ;
1#
#80290
0#
#80475
b11010111 ;
1#
#80660
0#
#80845
b11011000 ;
1#
#81030
0#
#81215
b11011001 ;
1#
#81400
0#
#81585
b11011010 ;
1#
#81770
0#
#81955
b11011011 ;
1#
#82140
0#
#82325
b11011100 ;
1#
#82510
0#
#82695
b11011101 ;
1#
#82880
0#
#83065
b11011110 ;
1#
#83250
0#
#83435
b11011111 ;
1#
#83620
0#
#83805
b11100000 ;
1#
#83990
0#
#84175
b11100001 ;
1#
#84360
0#
#84545
b11100010 ;
1#
#84730
0#
#84915
b11100011 ;
1#
#85100
0#
#85285
b11100100 ;
1#
#85470
0#
#85655
b11100101 ;
1#
#85840
0#
#86025
b11100110 ;
1#
#86210
0#
#86395
b11100111 ;
1#
#86580
0#
#86765
b11101000 ;
1#
#86950
0#
#87135
b11101001 ;
1#
#87320
0#
#87505
b11101010 ;
1#
#87690
0#
#87875
b11101011 ;
1#
#88060
0#
#88245
b11101100 ;
1#
#88430
0#
#88615
b11101101 ;
1#
#88800
0#
#88985
b11101110 ;
1#
#89170
0#
#89355
b11101111 ;
1#
#89540
0#
#89725
b11110000 ;
1#
#89910
0#
#90095
b11110001 ;
1#
#90280
0#
#90465
b11110010 ;
1#
#90650
0#
#90835
b11110011 ;
1#
#91020
0#
#91205
b11110100 ;
1#
#91390
0#
#91575
b11110101 ;
1#
#91760
0#
#91945
b11110110 ;
1#
#92130
0#
#92315
b11110111 ;
1#
#92500
0#
#92685
b11111000 ;
1#
#92870
0#
#93055
b11111001 ;
1#
#93240
0#
#93425
b11111010 ;
1#
#93610
0#
#93795
b11111011 ;
1#
#93980
0#
#94165
b11111100 ;
1#
#94350
0#
#94535
b11111101 ;
1#
#94720
0#
#94905
b11111110 ;
1#
#95090
0#
#95275
b11111111 ;
1#
#95460
0#
#95645
b100000000 ;
1#
#95830
0#
#96015
b100000001 ;
1#
#96200
0#
#96385
b100000010 ;
1#
#96570
0#
#96755
b100000011 ;
1#
#96940
0#
#97125
b100000100 ;
1#
#97310
0#
#97495
b100000101 ;
1#
#97680
0#
#97865
b100000110 ;
1#
#98050
0#
#98235
b100000111 ;
1#
#98420
0#
#98605
b100001000 ;
1#
#98790
0#
#98975
b100001001 ;
1#
#99160
0#
#99345
b100001010 ;
1#
#99530
0#
#99715
b100001011 ;
1#
#99900
0#
#100085
b100001100 ;
1#
#100270
0#
#100455
b100001101 ;
1#
#100640
0#
#100825
b100001110 ;
1#
#101010
0#
#101195
b100001111 ;
1#
#101380
0#
#101565
b100010000 ;
1#
#101750
0#
#101935
b100010001 ;
1#
#102120
0#
#102305
b100010010 ;
1#
#102490
0#
#102675
b100010011 ;
1#
#102860
0#
#103045
b100010100 ;
1#
#103230
0#
#103415
b100010101 ;
1#
#103600
0#
#103785
b100010110 ;
1#
#103970
0#
#104155
b100010111 ;
1#
#104340
0#
#104525
b100011000 ;
1#
#104710
0#
#104895
b100011001 ;
1#
#105080
0#
#105265
b100011010 ;
1#
#105450
0#
#105635
b100011011 ;
1#
#105820
0#
#106005
b100011100 ;
1#
#106190
0#
#106375
b100011101 ;
1#
#106560
0#
#106745
b100011110 ;
1#
#106930
0#
#107115
b100011111 ;
1#
#107300
0#
#107485
b100100000 ;
1#
#107670
0#
#107855
b100100001 ;
1#
#108040
0#
#108225
b100100010 ;
1#
#108410
0#
#108595
b100100011 ;
1#
#108780
0#
#108965
b100100100 ;
1#
#109150
0#
#109335
b100100101 ;
1#
#109520
0#
#109705
b100100110 ;
1#
#109890
0#
#110075
b100100111 ;
1#
#110260
0#
#110445
b100101000 ;
1#
#110630
0#
#110815
b100101001 ;
1#
#111000
0#
#111185
b100101010 ;
1#
#111370
0#
#111555
b100101011 ;
1#
#111740
0#
#111925
b100101100 ;
1#
#112110
0#
#112295
b100101101 ;
1#
#112480
0#
#112665
b100101110 ;
1#
#112850
0#
#113035
b100101111 ;
1#
#113220
0#
#113405
b100110000 ;
1#
#113590
0#
#113775
b100110001 ;
1#
#113960
0#
#114145
b100110010 ;
1#
#114330
0#
#114515
b100110011 ;
1#
#114700
0#
#114885
b100110100 ;
1#
#115070
0#
#115255
b100110101 ;
1#
#115440
0#
#115625
b100110110 ;
1#
#115810
0#
#115995
b100110111 ;
1#
#116180
0#
#116365
b100111000 ;
1#
#116550
0#
#116735
b100111001 ;
1#
#116920
0#
#117105
b100111010 ;
1#
#117290
0#
#117475
b100111011 ;
1#
#117660
0#
#117845
b100111100 ;
1#
#118030
0#
#118215
b100111101 ;
1#
#118400
0#
#118585
b100111110 ;
1#
#118770
0#
#118955
b100111111 ;
1#
#119140
0#
#119325
b101000000 ;
1#
#119510
0#
#119695
b101000001 ;
1#
#119880
0#
#120065
b101000010 ;
1#
#120250
0#
#120435
b101000011 ;
1#
#120620
0#
#120805
b101000100 ;
1#
#120990
0#
#121175
b101000101 ;
1#
#121360
0#
#121545
b101000110 ;
1#
#121730
0#
#121915
b101000111 ;
1#
#122100
0#
#122285
b101001000 ;
1#
#122470
0#
#122655
b101001001 ;
1#
#122840
0#
#123025
b101001010 ;
1#
#123210
0#
#123395
b101001011 ;
1#
#123580
0#
#123765
b101001100 ;
1#
#123950
0#
#124135
b101001101 ;
1#
#124320
0#
#124505
b101001110 ;
1#
#124690
0#
#124875
b101001111 ;
1#
#125060
0#
#125245
b101010000 ;
1#
#125430
0#
#125615
b101010001 ;
1#
#125800
0#
#125985
b101010010 ;
1#
#126170
0#
#126355
b101010011 ;
1#
#126540
0#
#126725
b101010100 ;
1#
#126910
0#
#127095
b101010101 ;
1#
#127280
0#
#127465
b101010110 ;
1#
#127650
0#
#127835
b101010111 ;
1#
#128020
0#
#128205
b101011000 ;
1#
#128390
0#
#128575
b101011001 ;
1#
#128760
0#
#128945
b101011010 ;
1#
#129130
0#
#129315
b101011011 ;
1#
#129500
0#
#129685
b101011100 ;
1#
#129870
0#
#130055
b101011101 ;
1#
#130240
0#
#130425
b101011110 ;
1#
#130610
0#
#130795
b101011111 ;
1#
#130980
0#
#131165
b101100000 ;
1#
#131350
0#
#131535
b101100001 ;
1#
#131720
0#
#131905
b101100010 ;
1#
#132090
0#
#132275
b101100011 ;
1#
#132460
0#
#132645
b101100100 ;
1#
#132830
0#
#133015
b101100101 ;
1#
#133200
0#
#133385
b101100110 ;
1#
#133570
0#
#133755
b101100111 ;
1#
#133940
0#
#134125
b101101000 ;
1#
#134310
0#
#134495
b101101001 ;
1#
#134680
0#
#134865
b101101010 ;
1#
#135050
0#
#135235
b101101011 ;
1#
#135420
0#
#135605
b101101100 ;
1#
#135790
0#
#135975
b101101101 ;
1#
#136160
0#
#136345
b101101110 ;
1#
#136530
0#
#136715
b101101111 ;
1#
#136900
0#
#137085
b101110000 ;
1#
#137270
0#
#137455
b101110001 ;
1#
#137640
0#
#137825
b101110010 ;
1#
#138010
0#
#138195
b101110011 ;
1#
#138380
0#
#138565
b101110100 ;
1#
#138750
0#
#138935
b101110101 ;
1#
#139120
0#
#139305
b101110110 ;
1#
#139490
0#
#139675
b101110111 ;
1#
#139860
0#
#140045
b101111000 ;
1#
#140230
0#
#140415
b101111001 ;
1#
#140600
0#
#140785
b101111010 ;
1#
#140970
0#
#141155
b101111011 ;
1#
#141340
0#
#141525
b101111100 ;
1#
#141710
0#
#141895
b101111101 ;
1#
#142080
0#
#142265
b101111110 ;
1#
#142450
0#
#142635
b101111111 ;
1#
#142820
0#
#143005
b110000000 ;
1#
#143190
0#
#143375
b110000001 ;
1#
#143560
0#
#143745
b110000010 ;
1#
#143930
0#
#144115
b110000011 ;
1#
#144300
0#
#144485
b110000100 ;
1#
#144670
0#
#144855
b110000101 ;
1#
#145040
0#
#145225
b110000110 ;
1#
#145410
0#
#145595
b110000111 ;
1#
#145780
0#
#145965
b110001000 ;
1#
#146150
0#
#146335
b110001001 ;
1#
#146520
0#
#146705
b110001010 ;
1#
#146890
0#
#147075
b110001011 ;
1#
#147260
0#
#147445
b110001100 ;
1#
#147630
0#
#147815
b110001101 ;
1#
#148000
0#
#148185
b110001110 ;
1#
#148370
0#
#148555
b110001111 ;
1#
#148740
0#
#148925
b110010000 ;
1#
#149110
0#
#149295
b110010001 ;
1#
#149480
0#
#149665
b110010010 ;
1#
#149850
0#
#150035
b110010011 ;
1#
#150220
0#
#150405
b110010100 ;
1#
#150590
0#
#150775
b110010101 ;
1#
#150960
0#
#151145
b110010110 ;
1#
#151330
0#
#151515
b110010111 ;
1#
#151700
0#
#151885
b110011000 ;
1#
#152070
0#
#152255
b110011001 ;
1#
#152440
0#
#152625
b110011010 ;
1#
#152810
0#
#152995
b110011011 ;
1#
#153180
0#
#153365
b110011100 ;
1#
#153550
0#
#153735
b110011101 ;
1#
#153920
0#
#154105
b110011110 ;
1#
#154290
0#
#154475
b110011111 ;
1#
#154660
0#
#154845
b110100000 ;
1#
#155030
0#
#155215
b110100001 ;
1#
#155400
0#
#155585
b110100010 ;
1#
#155770
0#
#155955
b110100011 ;
1#
#156140
0#
#156325
b110100100 ;
1#
#156510
0#
#156695
b110100101 ;
1#
#156880
0#
#157065
b110100110 ;
1#
#157250
0#
#157435
b110100111 ;
1#
#157620
0#
#157805
b110101000 ;
1#
#157990
0#
#158175
b110101001 ;
1#
#158360
0#
#158545
b110101010 ;
1#
#158730
0#
#158915
b110101011 ;
1#
#159100
0#
#159285
b110101100 ;
1#
#159470
0#
#159655
b110101101 ;
1#
#159840
0#
#160025
b110101110 ;
1#
#160210
0#
#160395
b110101111 ;
1#
#160580
0#
#160765
b110110000 ;
1#
#160950
0#
#161135
b110110001 ;
1#
#161320
0#
#161505
b110110010 ;
1#
#161690
0#
#161875
b110110011 ;
1#
#162060
0#
#162245
b110110100 ;
1#
#162430
0#
#162615
b110110101 ;
1#
#162800
0#
#162985
b110110110 ;
1#
#163170
0#
#163355
b110110111 ;
1#
#163540
0#
#163725
b110111000 ;
1#
#163910
0#
#164095
b110111001 ;
1#
#164280
0#
#164465
b110111010 ;
1#
#164650
0#
#164835
b110111011 ;
1#
#165020
0#
#165205
b110111100 ;
1#
#165390
0#
#165575
b110111101 ;
1#
#165760
0#
#165945
b110111110 ;
1#
#166130
0#
#166315
b110111111 ;
1#
#166500
0#
#166685
b111000000 ;
1#
#166870
0#
#167055
b111000001 ;
1#
#167240
0#
#167425
b111000010 ;
1#
#167610
0#
#167795
b111000011 ;
1#
#167980
0#
#168165
b111000100 ;
1#
#168350
0#
#168535
b111000101 ;
1#
#168720
0#
#168905
b111000110 ;
1#
#169090
0#
